{"Patient 0": {"criticality": "Level 2", "Registration": {"arrival": "07:36:35 AM", "start": "07:36:35 AM", "finish": "07:43:39 AM", "delay": "0:00:00"}, "Bedspace Allocation": {"arrival": "07:43:39 AM", "start": "08:00:39 AM", "finish": "08:06:44 AM", "delay": "0:17:00", "occupancy": "364.89 seconds"}}, "Patient 1": {"criticality": "Level 1", "Bedspace Allocation": {"arrival": "07:38:35 AM", "start": "08:00:35 AM", "finish": "08:06:39 AM", "delay": "0:22:00", "occupancy": "364.10 seconds"}, "Registration": {"arrival": "08:06:39 AM", "start": "08:06:39 AM", "finish": "08:13:42 AM", "delay": "0:00:00"}, "Consultation": {"arrival": "08:13:42 AM", "start": "08:13:42 AM", "finish": "08:27:45 AM", "delay": "0:00:00"}, "Billing": {"arrival": "08:27:45 AM", "start": "08:27:45 AM", "finish": "08:37:47 AM", "delay": "0:00:00"}, "Pharmacy": {"arrival": "08:37:47 AM", "start": "08:37:47 AM", "finish": "08:52:48 AM", "delay": "0:00:00"}}, "Patient 2": {"criticality": "Level 3", "Registration": {"arrival": "07:40:21 AM", "start": "07:40:21 AM", "finish": "07:47:22 AM", "delay": "0:00:00"}, "Bedspace Allocation": {"arrival": "07:47:22 AM", "start": "08:00:22 AM", "finish": "08:06:23 AM", "delay": "0:13:00", "occupancy": "360.53 seconds"}, "Consultation": {"arrival": "08:06:23 AM", "start": "08:06:23 AM", "finish": "08:20:23 AM", "delay": "0:00:00"}, "Billing": {"arrival": "08:20:23 AM", "start": "08:20:23 AM", "finish": "08:30:24 AM", "delay": "0:00:00"}, "Pharmacy": {"arrival": "08:30:24 AM", "start": "08:30:24 AM", "finish": "08:45:27 AM", "delay": "0:00:00"}}, "Patient 3": {"criticality": "Level 1", "Bedspace Allocation": {"arrival": "07:51:21 AM", "start": "08:00:21 AM", "finish": "08:06:23 AM", "delay": "0:09:00", "occupancy": "362.38 seconds"}, "Registration": {"arrival": "08:06:23 AM", "start": "08:06:23 AM", "finish": "08:13:24 AM", "delay": "0:00:00"}, "Billing": {"arrival": "08:13:24 AM", "start": "08:13:24 AM", "finish": "08:23:24 AM", "delay": "0:00:00"}, "Xray": {"arrival": "08:23:24 AM", "start": "08:23:24 AM", "finish": "08:44:25 AM", "delay": "0:00:00"}}, "Patient 4": {"criticality": "Level 3", "Registration": {"arrival": "07:53:37 AM", "start": "07:53:37 AM", "finish": "08:00:37 AM", "delay": "0:00:00"}, "Bedspace Allocation": {"arrival": "08:00:37 AM", "start": "08:00:37 AM", "finish": "08:06:42 AM", "delay": "0:00:00", "occupancy": "364.91 seconds"}, "Consultation": {"arrival": "08:51:48 AM", "start": "08:51:48 AM", "finish": "09:05:52 AM", "delay": "0:00:00"}, "Billing": {"arrival": "08:20:46 AM", "start": "08:20:46 AM", "finish": "08:30:46 AM", "delay": "0:00:00"}, "Xray": {"arrival": "08:30:46 AM", "start": "08:30:46 AM", "finish": "08:51:48 AM", "delay": "0:00:00"}}, "Patient 5": {"criticality": "Level 2", "Registration": {"arrival": "08:04:27 AM", "start": "08:04:27 AM", "finish": "08:11:31 AM", "delay": "0:00:00"}, "Bedspace Allocation": {"arrival": "08:11:31 AM", "start": "08:11:31 AM", "finish": "08:17:34 AM", "delay": "0:00:00", "occupancy": "363.01 seconds"}, "Xray": {"arrival": "08:17:34 AM", "start": "08:17:34 AM", "finish": "08:38:37 AM", "delay": "0:00:00"}}, "Patient 6": {"criticality": "Level 2", "Registration": {"arrival": "08:06:30 AM", "start": "08:06:30 AM", "finish": "08:13:31 AM", "delay": "0:00:00"}, "Bedspace Allocation": {"arrival": "08:13:31 AM", "start": "08:13:31 AM", "finish": "08:19:34 AM", "delay": "0:00:00", "occupancy": "362.61 seconds"}, "Xray": {"arrival": "08:19:34 AM", "start": "08:19:34 AM", "finish": "08:40:34 AM", "delay": "0:00:00"}}, "Patient 7": {"criticality": "Level 1", "Bedspace Allocation": {"arrival": "08:08:27 AM", "start": "08:08:27 AM", "finish": "08:14:29 AM", "delay": "0:00:00", "occupancy": "362.13 seconds"}, "Registration": {"arrival": "08:14:29 AM", "start": "08:14:29 AM", "finish": "08:21:30 AM", "delay": "0:00:00"}, "Scan": {"arrival": "08:21:30 AM", "start": "08:21:30 AM", "finish": "08:49:34 AM", "delay": "0:00:00"}}, "Patient 8": {"criticality": "Level 2", "Registration": {"arrival": "08:10:39 AM", "start": "08:10:39 AM", "finish": "08:17:42 AM", "delay": "0:00:00"}, "Bedspace Allocation": {"arrival": "08:17:42 AM", "start": "08:17:42 AM", "finish": "08:23:43 AM", "delay": "0:00:00", "occupancy": "360.65 seconds"}, "Consultation": {"arrival": "08:23:43 AM", "start": "08:23:43 AM", "finish": "08:37:47 AM", "delay": "0:00:00"}, "Billing": {"arrival": "08:37:47 AM", "start": "08:37:47 AM", "finish": "08:47:51 AM", "delay": "0:00:00"}, "Pharmacy": {"arrival": "08:47:51 AM", "start": "08:47:51 AM", "finish": "09:02:54 AM", "delay": "0:00:00"}, "Dressing": {"arrival": "09:02:54 AM", "start": "09:08:36 AM", "finish": "09:23:41 AM", "delay": "0:05:42.085897"}}, "Patient 9": {"criticality": "Level 3", "Registration": {"arrival": "08:12:30 AM", "start": "08:12:30 AM", "finish": "08:19:30 AM", "delay": "0:00:00"}, "Bedspace Allocation": {"arrival": "08:19:30 AM", "start": "08:19:30 AM", "finish": "08:25:31 AM", "delay": "0:00:00", "occupancy": "360.42 seconds"}, "Consultation": {"arrival": "08:25:31 AM", "start": "08:25:31 AM", "finish": "08:39:35 AM", "delay": "0:00:00"}, "Billing": {"arrival": "09:10:39 AM", "start": "09:10:39 AM", "finish": "09:20:43 AM", "delay": "0:00:00"}, "Xray": {"arrival": "08:49:37 AM", "start": "08:49:37 AM", "finish": "09:10:39 AM", "delay": "0:00:00"}, "Pharmacy": {"arrival": "09:20:43 AM", "start": "09:20:43 AM", "finish": "09:35:45 AM", "delay": "0:00:00"}, "Dressing": {"arrival": "09:35:45 AM", "start": "10:08:48 AM", "finish": "10:23:51 AM", "delay": "0:33:03.767473"}}, "Patient 10": {"criticality": "Level 1", "Bedspace Allocation": {"arrival": "08:16:28 AM", "start": "08:16:28 AM", "finish": "08:22:28 AM", "delay": "0:00:00", "occupancy": "360.49 seconds"}, "Registration": {"arrival": "08:22:28 AM", "start": "08:22:28 AM", "finish": "08:29:31 AM", "delay": "0:00:00"}, "Consultation": {"arrival": "08:29:31 AM", "start": "08:29:31 AM", "finish": "08:43:31 AM", "delay": "0:00:00"}, "Billing": {"arrival": "08:43:31 AM", "start": "08:43:31 AM", "finish": "08:53:34 AM", "delay": "0:00:00"}, "Dressing": {"arrival": "08:53:34 AM", "start": "08:53:34 AM", "finish": "09:08:36 AM", "delay": "0:00:00"}}, "Patient 11": {"criticality": "Level 2", "Registration": {"arrival": "08:17:34 AM", "start": "08:17:34 AM", "finish": "08:24:36 AM", "delay": "0:00:00"}, "Bedspace Allocation": {"arrival": "08:24:36 AM", "start": "08:24:36 AM", "finish": "08:30:39 AM", "delay": "0:00:00", "occupancy": "363.38 seconds"}, "Consultation": {"arrival": "08:30:39 AM", "start": "08:30:39 AM", "finish": "08:44:41 AM", "delay": "0:00:00"}, "Billing": {"arrival": "08:44:41 AM", "start": "08:44:41 AM", "finish": "08:54:42 AM", "delay": "0:00:00"}, "Pharmacy": {"arrival": "08:54:42 AM", "start": "08:54:42 AM", "finish": "09:09:42 AM", "delay": "0:00:00"}}, "Patient 12": {"criticality": "Level 2", "Registration": {"arrival": "08:21:05 AM", "start": "08:21:05 AM", "finish": "08:28:05 AM", "delay": "0:00:00"}, "Bedspace Allocation": {"arrival": "08:28:05 AM", "start": "08:28:05 AM", "finish": "08:34:08 AM", "delay": "0:00:00", "occupancy": "363.64 seconds"}, "Consultation": {"arrival": "08:34:08 AM", "start": "08:34:08 AM", "finish": "08:48:09 AM", "delay": "0:00:00"}, "Billing": {"arrival": "08:48:09 AM", "start": "08:48:09 AM", "finish": "08:58:13 AM", "delay": "0:00:00"}, "Pharmacy": {"arrival": "08:58:13 AM", "start": "08:58:13 AM", "finish": "09:13:18 AM", "delay": "0:00:00"}, "Dressing": {"arrival": "09:13:18 AM", "start": "09:38:42 AM", "finish": "09:53:44 AM", "delay": "0:25:23.906029"}}, "Patient 13": {"criticality": "Level 1", "Bedspace Allocation": {"arrival": "08:22:57 AM", "start": "08:22:57 AM", "finish": "08:28:58 AM", "delay": "0:00:00", "occupancy": "361.52 seconds"}, "Registration": {"arrival": "08:28:58 AM", "start": "08:28:58 AM", "finish": "08:36:03 AM", "delay": "0:00:00"}, "Consultation": {"arrival": "08:36:03 AM", "start": "08:36:03 AM", "finish": "08:50:03 AM", "delay": "0:00:00"}, "Billing": {"arrival": "08:50:03 AM", "start": "08:50:03 AM", "finish": "09:00:04 AM", "delay": "0:00:00"}, "Pharmacy": {"arrival": "09:00:04 AM", "start": "09:00:04 AM", "finish": "09:15:06 AM", "delay": "0:00:00"}}, "Patient 14": {"criticality": "Level 3", "Registration": {"arrival": "08:25:31 AM", "start": "08:25:31 AM", "finish": "08:32:31 AM", "delay": "0:00:00"}, "Bedspace Allocation": {"arrival": "08:32:31 AM", "start": "08:32:31 AM", "finish": "08:38:32 AM", "delay": "0:00:00", "occupancy": "361.27 seconds"}, "Consultation": {"arrival": "08:38:32 AM", "start": "08:38:32 AM", "finish": "08:52:34 AM", "delay": "0:00:00"}, "Billing": {"arrival": "09:24:36 AM", "start": "09:24:36 AM", "finish": "09:34:39 AM", "delay": "0:00:00"}, "Xray": {"arrival": "09:03:34 AM", "start": "09:03:34 AM", "finish": "09:24:36 AM", "delay": "0:00:00"}, "Pharmacy": {"arrival": "09:34:39 AM", "start": "09:34:39 AM", "finish": "09:49:40 AM", "delay": "0:00:00"}, "Dressing": {"arrival": "09:49:40 AM", "start": "10:23:51 AM", "finish": "10:38:53 AM", "delay": "0:34:11.668919"}}, "Patient 15": {"criticality": "Level 3", "Registration": {"arrival": "08:31:49 AM", "start": "08:31:49 AM", "finish": "08:38:49 AM", "delay": "0:00:00"}, "Bedspace Allocation": {"arrival": "08:38:49 AM", "start": "08:38:49 AM", "finish": "08:44:51 AM", "delay": "0:00:00", "occupancy": "361.82 seconds"}, "Consultation": {"arrival": "08:44:51 AM", "start": "08:44:51 AM", "finish": "08:58:53 AM", "delay": "0:00:00"}, "Billing": {"arrival": "08:58:53 AM", "start": "08:58:53 AM", "finish": "09:08:56 AM", "delay": "0:00:00"}, "Pharmacy": {"arrival": "09:08:56 AM", "start": "09:08:56 AM", "finish": "09:23:57 AM", "delay": "0:00:00"}}, "Patient 16": {"criticality": "Level 2", "Registration": {"arrival": "08:34:47 AM", "start": "08:34:47 AM", "finish": "08:41:47 AM", "delay": "0:00:00"}, "Bedspace Allocation": {"arrival": "08:41:47 AM", "start": "08:41:47 AM", "finish": "08:47:52 AM", "delay": "0:00:00", "occupancy": "364.93 seconds"}, "Consultation": {"arrival": "08:47:52 AM", "start": "08:47:52 AM", "finish": "09:01:54 AM", "delay": "0:00:00"}, "Billing": {"arrival": "09:01:54 AM", "start": "09:01:54 AM", "finish": "09:11:59 AM", "delay": "0:00:00"}, "Dressing": {"arrival": "09:11:59 AM", "start": "09:23:41 AM", "finish": "09:38:42 AM", "delay": "0:11:42.072657"}}, "Patient 17": {"criticality": "Level 2", "Registration": {"arrival": "08:38:51 AM", "start": "08:38:51 AM", "finish": "08:45:51 AM", "delay": "0:00:00"}, "Bedspace Allocation": {"arrival": "08:45:51 AM", "start": "08:45:51 AM", "finish": "08:51:56 AM", "delay": "0:00:00", "occupancy": "364.89 seconds"}, "Consultation": {"arrival": "08:51:56 AM", "start": "08:51:56 AM", "finish": "09:05:58 AM", "delay": "0:00:00"}, "Billing": {"arrival": "09:05:58 AM", "start": "09:05:58 AM", "finish": "09:15:59 AM", "delay": "0:00:00"}, "Pharmacy": {"arrival": "09:15:59 AM", "start": "09:15:59 AM", "finish": "09:31:02 AM", "delay": "0:00:00"}, "Dressing": {"arrival": "09:31:02 AM", "start": "09:53:44 AM", "finish": "10:08:48 AM", "delay": "0:22:41.705799"}}, "Patient 18": {"criticality": "Level 2", "Registration": {"arrival": "08:39:38 AM", "start": "08:39:38 AM", "finish": "08:46:41 AM", "delay": "0:00:00"}, "Bedspace Allocation": {"arrival": "08:46:41 AM", "start": "08:46:41 AM", "finish": "08:52:42 AM", "delay": "0:00:00", "occupancy": "361.25 seconds"}, "Consultation": {"arrival": "08:52:42 AM", "start": "08:52:42 AM", "finish": "09:06:43 AM", "delay": "0:00:00"}, "Billing": {"arrival": "09:06:43 AM", "start": "09:06:43 AM", "finish": "09:16:46 AM", "delay": "0:00:00"}, "Pharmacy": {"arrival": "09:16:46 AM", "start": "09:16:46 AM", "finish": "09:31:47 AM", "delay": "0:00:00"}}, "Patient 19": {"criticality": "Level 3", "Registration": {"arrival": "08:44:43 AM", "start": "08:44:43 AM", "finish": "08:51:47 AM", "delay": "0:00:00"}, "Bedspace Allocation": {"arrival": "08:51:47 AM", "start": "08:51:47 AM", "finish": "08:57:50 AM", "delay": "0:00:00", "occupancy": "362.79 seconds"}, "Consultation": {"arrival": "08:57:50 AM", "start": "08:57:50 AM", "finish": "09:11:53 AM", "delay": "0:00:00"}, "Billing": {"arrival": "09:11:53 AM", "start": "09:11:59 AM", "finish": "09:22:02 AM", "delay": "0:00:06.363479"}, "Injection": {"arrival": "09:22:02 AM", "start": "09:22:02 AM", "finish": "09:33:05 AM", "delay": "0:00:00"}}, "Patient 20": {"criticality": "Level 3", "Registration": {"arrival": "08:47:38 AM", "start": "08:47:38 AM", "finish": "08:54:38 AM", "delay": "0:00:00"}, "Bedspace Allocation": {"arrival": "08:54:38 AM", "start": "08:54:38 AM", "finish": "09:00:42 AM", "delay": "0:00:00", "occupancy": "364.24 seconds"}, "Consultation": {"arrival": "09:47:04 AM", "start": "09:47:04 AM", "finish": "10:01:08 AM", "delay": "0:00:00"}, "Billing": {"arrival": "10:01:08 AM", "start": "10:01:08 AM", "finish": "10:11:08 AM", "delay": "0:00:00"}, "Xray": {"arrival": "09:26:03 AM", "start": "09:26:03 AM", "finish": "09:47:04 AM", "delay": "0:00:00"}, "Pharmacy": {"arrival": "10:11:08 AM", "start": "10:11:08 AM", "finish": "10:26:08 AM", "delay": "0:00:00"}, "Dressing": {"arrival": "10:26:08 AM", "start": "11:09:01 AM", "finish": "11:24:04 AM", "delay": "0:42:52.325263"}}, "Patient 21": {"criticality": "Level 1", "Bedspace Allocation": {"arrival": "08:50:50 AM", "start": "08:50:50 AM", "finish": "08:56:52 AM", "delay": "0:00:00", "occupancy": "362.03 seconds"}, "Registration": {"arrival": "08:56:52 AM", "start": "08:56:52 AM", "finish": "09:03:56 AM", "delay": "0:00:00"}, "Consultation": {"arrival": "09:49:06 AM", "start": "09:49:06 AM", "finish": "10:03:07 AM", "delay": "0:00:00"}, "Billing": {"arrival": "10:03:07 AM", "start": "10:06:55 AM", "finish": "10:16:55 AM", "delay": "0:03:47.220166"}, "Xray": {"arrival": "09:28:03 AM", "start": "09:28:03 AM", "finish": "09:49:06 AM", "delay": "0:00:00"}, "Pharmacy": {"arrival": "10:16:55 AM", "start": "10:16:55 AM", "finish": "10:31:56 AM", "delay": "0:00:00"}, "Dressing": {"arrival": "10:31:56 AM", "start": "11:39:07 AM", "finish": "11:54:08 AM", "delay": "1:07:11.498964"}}, "Patient 22": {"criticality": "Level 3", "Registration": {"arrival": "08:55:27 AM", "start": "08:55:27 AM", "finish": "09:02:28 AM", "delay": "0:00:00"}, "Bedspace Allocation": {"arrival": "09:02:28 AM", "start": "09:02:28 AM", "finish": "09:08:31 AM", "delay": "0:00:00", "occupancy": "362.53 seconds"}, "Consultation": {"arrival": "09:08:31 AM", "start": "09:08:31 AM", "finish": "09:22:33 AM", "delay": "0:00:00"}, "Billing": {"arrival": "09:22:33 AM", "start": "09:22:33 AM", "finish": "09:32:35 AM", "delay": "0:00:00"}, "Pharmacy": {"arrival": "09:32:35 AM", "start": "09:32:35 AM", "finish": "09:47:35 AM", "delay": "0:00:00"}}, "Patient 23": {"criticality": "Level 1", "Bedspace Allocation": {"arrival": "09:00:35 AM", "start": "09:00:35 AM", "finish": "09:06:35 AM", "delay": "0:00:00", "occupancy": "360.25 seconds"}, "Registration": {"arrival": "09:06:35 AM", "start": "09:06:35 AM", "finish": "09:13:37 AM", "delay": "0:00:00"}, "Consultation": {"arrival": "09:13:37 AM", "start": "09:13:37 AM", "finish": "09:27:37 AM", "delay": "0:00:00"}, "Billing": {"arrival": "09:27:37 AM", "start": "09:27:37 AM", "finish": "09:37:41 AM", "delay": "0:00:00"}, "Injection": {"arrival": "09:37:41 AM", "start": "09:37:41 AM", "finish": "09:48:46 AM", "delay": "0:00:00"}}, "Patient 24": {"criticality": "Level 2", "Registration": {"arrival": "09:01:47 AM", "start": "09:01:47 AM", "finish": "09:08:48 AM", "delay": "0:00:00"}, "Bedspace Allocation": {"arrival": "09:08:48 AM", "start": "09:08:48 AM", "finish": "09:14:51 AM", "delay": "0:00:00", "occupancy": "362.83 seconds"}, "Consultation": {"arrival": "09:14:51 AM", "start": "09:14:51 AM", "finish": "09:28:53 AM", "delay": "0:00:00"}, "Billing": {"arrival": "10:03:37 AM", "start": "10:09:22 AM", "finish": "10:19:26 AM", "delay": "0:05:45.638932"}, "Xray": {"arrival": "09:42:36 AM", "start": "09:42:36 AM", "finish": "10:03:37 AM", "delay": "0:00:00"}, "Pharmacy": {"arrival": "10:19:26 AM", "start": "10:19:26 AM", "finish": "10:34:29 AM", "delay": "0:00:00"}}, "Patient 25": {"criticality": "Level 2", "Registration": {"arrival": "09:07:01 AM", "start": "09:07:01 AM", "finish": "09:14:02 AM", "delay": "0:00:00"}, "Bedspace Allocation": {"arrival": "09:14:02 AM", "start": "09:14:02 AM", "finish": "09:20:03 AM", "delay": "0:00:00", "occupancy": "361.06 seconds"}, "Consultation": {"arrival": "09:20:03 AM", "start": "09:20:03 AM", "finish": "09:34:05 AM", "delay": "0:00:00"}, "Billing": {"arrival": "09:34:05 AM", "start": "09:37:41 AM", "finish": "09:47:43 AM", "delay": "0:03:36.889750"}, "Pharmacy": {"arrival": "09:47:43 AM", "start": "09:47:43 AM", "finish": "10:02:45 AM", "delay": "0:00:00"}}, "Patient 26": {"criticality": "Level 1", "Bedspace Allocation": {"arrival": "09:09:46 AM", "start": "09:09:46 AM", "finish": "09:15:49 AM", "delay": "0:00:00", "occupancy": "363.91 seconds"}, "Registration": {"arrival": "09:15:49 AM", "start": "09:15:49 AM", "finish": "09:22:53 AM", "delay": "0:00:00"}, "Consultation": {"arrival": "09:22:53 AM", "start": "09:22:53 AM", "finish": "09:36:56 AM", "delay": "0:00:00"}}, "Patient 27": {"criticality": "Level 2", "Registration": {"arrival": "09:15:17 AM", "start": "09:15:17 AM", "finish": "09:22:20 AM", "delay": "0:00:00"}, "Bedspace Allocation": {"arrival": "09:22:20 AM", "start": "09:22:20 AM", "finish": "09:28:23 AM", "delay": "0:00:00", "occupancy": "362.92 seconds"}, "Billing": {"arrival": "09:28:23 AM", "start": "09:28:23 AM", "finish": "09:38:24 AM", "delay": "0:00:00"}, "Xray": {"arrival": "09:38:24 AM", "start": "09:38:24 AM", "finish": "09:59:26 AM", "delay": "0:00:00"}}, "Patient 28": {"criticality": "Level 3", "Registration": {"arrival": "09:17:00 AM", "start": "09:17:00 AM", "finish": "09:24:04 AM", "delay": "0:00:00"}, "Bedspace Allocation": {"arrival": "09:24:04 AM", "start": "09:24:04 AM", "finish": "09:30:05 AM", "delay": "0:00:00", "occupancy": "360.59 seconds"}, "Billing": {"arrival": "10:22:10 AM", "start": "10:29:27 AM", "finish": "10:39:32 AM", "delay": "0:07:17.549035"}, "Xray": {"arrival": "09:44:44 AM", "start": "09:47:04 AM", "finish": "10:08:05 AM", "delay": "0:02:20.027947"}, "Consultation": {"arrival": "10:08:05 AM", "start": "10:08:05 AM", "finish": "10:22:10 AM", "delay": "0:00:00"}, "Pharmacy": {"arrival": "10:39:32 AM", "start": "10:39:32 AM", "finish": "10:54:33 AM", "delay": "0:00:00"}}, "Patient 29": {"criticality": "Level 3", "Registration": {"arrival": "09:23:27 AM", "start": "09:23:27 AM", "finish": "09:30:28 AM", "delay": "0:00:00"}, "Bedspace Allocation": {"arrival": "09:30:28 AM", "start": "09:30:28 AM", "finish": "09:36:29 AM", "delay": "0:00:00", "occupancy": "360.87 seconds"}, "Consultation": {"arrival": "09:36:29 AM", "start": "09:36:29 AM", "finish": "09:50:31 AM", "delay": "0:00:00"}, "Billing": {"arrival": "09:50:31 AM", "start": "09:50:31 AM", "finish": "10:00:36 AM", "delay": "0:00:00"}, "Pharmacy": {"arrival": "10:00:36 AM", "start": "10:00:36 AM", "finish": "10:15:40 AM", "delay": "0:00:00"}}, "Patient 30": {"criticality": "Level 2", "Registration": {"arrival": "09:24:13 AM", "start": "09:24:13 AM", "finish": "09:31:13 AM", "delay": "0:00:00"}, "Bedspace Allocation": {"arrival": "09:31:13 AM", "start": "09:31:13 AM", "finish": "09:37:18 AM", "delay": "0:00:00", "occupancy": "364.46 seconds"}, "Consultation": {"arrival": "09:37:18 AM", "start": "09:37:18 AM", "finish": "09:51:19 AM", "delay": "0:00:00"}}, "Patient 31": {"criticality": "Level 2", "Registration": {"arrival": "09:27:07 AM", "start": "09:27:07 AM", "finish": "09:34:08 AM", "delay": "0:00:00"}, "Bedspace Allocation": {"arrival": "09:34:08 AM", "start": "09:34:08 AM", "finish": "09:40:10 AM", "delay": "0:00:00", "occupancy": "361.60 seconds"}}, "Patient 32": {"criticality": "Level 3", "Registration": {"arrival": "09:29:43 AM", "start": "09:29:43 AM", "finish": "09:36:46 AM", "delay": "0:00:00"}, "Bedspace Allocation": {"arrival": "09:36:46 AM", "start": "09:36:46 AM", "finish": "09:42:47 AM", "delay": "0:00:00", "occupancy": "361.38 seconds"}, "Consultation": {"arrival": "09:42:47 AM", "start": "09:42:47 AM", "finish": "09:56:51 AM", "delay": "0:00:00"}, "Billing": {"arrival": "09:56:51 AM", "start": "09:56:51 AM", "finish": "10:06:55 AM", "delay": "0:00:00"}, "Dressing": {"arrival": "10:06:55 AM", "start": "10:38:53 AM", "finish": "10:53:56 AM", "delay": "0:31:58.275416"}}, "Patient 33": {"criticality": "Level 1", "Bedspace Allocation": {"arrival": "09:32:10 AM", "start": "09:32:10 AM", "finish": "09:38:14 AM", "delay": "0:00:00", "occupancy": "364.38 seconds"}, "Registration": {"arrival": "09:38:14 AM", "start": "09:38:14 AM", "finish": "09:45:17 AM", "delay": "0:00:00"}, "Consultation": {"arrival": "09:45:17 AM", "start": "09:45:17 AM", "finish": "09:59:21 AM", "delay": "0:00:00"}, "Billing": {"arrival": "09:59:21 AM", "start": "09:59:21 AM", "finish": "10:09:22 AM", "delay": "0:00:00"}, "Dressing": {"arrival": "10:09:22 AM", "start": "10:53:56 AM", "finish": "11:09:01 AM", "delay": "0:44:33.327450"}}, "Patient 34": {"criticality": "Level 1", "Bedspace Allocation": {"arrival": "09:34:54 AM", "start": "09:34:54 AM", "finish": "09:40:54 AM", "delay": "0:00:00", "occupancy": "360.53 seconds"}, "Registration": {"arrival": "09:40:54 AM", "start": "09:40:54 AM", "finish": "09:47:57 AM", "delay": "0:00:00"}, "Consultation": {"arrival": "10:33:09 AM", "start": "10:33:09 AM", "finish": "10:47:13 AM", "delay": "0:00:00"}, "Billing": {"arrival": "10:47:13 AM", "start": "10:48:45 AM", "finish": "10:58:49 AM", "delay": "0:01:32.073919"}, "Xray": {"arrival": "10:12:05 AM", "start": "10:12:05 AM", "finish": "10:33:09 AM", "delay": "0:00:00"}, "Pharmacy": {"arrival": "10:58:49 AM", "start": "10:58:49 AM", "finish": "11:13:51 AM", "delay": "0:00:00"}}, "Patient 35": {"criticality": "Level 2", "Registration": {"arrival": "09:44:10 AM", "start": "09:44:10 AM", "finish": "09:51:12 AM", "delay": "0:00:00"}, "Bedspace Allocation": {"arrival": "09:51:12 AM", "start": "09:51:12 AM", "finish": "09:57:16 AM", "delay": "0:00:00", "occupancy": "364.53 seconds"}, "Consultation": {"arrival": "09:57:16 AM", "start": "09:57:16 AM", "finish": "10:11:19 AM", "delay": "0:00:00"}, "Billing": {"arrival": "10:11:19 AM", "start": "10:12:05 AM", "finish": "10:22:08 AM", "delay": "0:00:46.504429"}, "Injection": {"arrival": "10:22:08 AM", "start": "10:22:08 AM", "finish": "10:33:12 AM", "delay": "0:00:00"}}, "Patient 36": {"criticality": "Level 1", "Bedspace Allocation": {"arrival": "09:46:04 AM", "start": "09:46:04 AM", "finish": "09:52:07 AM", "delay": "0:00:00", "occupancy": "363.97 seconds"}, "Registration": {"arrival": "09:52:07 AM", "start": "09:52:07 AM", "finish": "09:59:12 AM", "delay": "0:00:00"}, "Consultation": {"arrival": "09:59:12 AM", "start": "09:59:12 AM", "finish": "10:13:13 AM", "delay": "0:00:00"}, "Billing": {"arrival": "10:13:13 AM", "start": "10:16:55 AM", "finish": "10:26:57 AM", "delay": "0:03:42.006451"}, "Injection": {"arrival": "10:26:57 AM", "start": "10:33:12 AM", "finish": "10:44:13 AM", "delay": "0:06:14.477658"}}, "Patient 37": {"criticality": "Level 1", "Bedspace Allocation": {"arrival": "09:46:51 AM", "start": "09:46:51 AM", "finish": "09:52:51 AM", "delay": "0:00:00", "occupancy": "360.26 seconds"}, "Registration": {"arrival": "09:52:51 AM", "start": "09:57:27 AM", "finish": "10:04:31 AM", "delay": "0:04:35.853428"}, "Consultation": {"arrival": "10:04:31 AM", "start": "10:04:31 AM", "finish": "10:18:34 AM", "delay": "0:00:00"}, "Billing": {"arrival": "10:18:34 AM", "start": "10:21:09 AM", "finish": "10:31:10 AM", "delay": "0:02:35.635048"}, "Dressing": {"arrival": "10:31:10 AM", "start": "11:24:04 AM", "finish": "11:39:07 AM", "delay": "0:52:53.413531"}}, "Patient 38": {"criticality": "Level 3", "Registration": {"arrival": "09:50:25 AM", "start": "09:50:25 AM", "finish": "09:57:27 AM", "delay": "0:00:00"}, "Bedspace Allocation": {"arrival": "09:57:27 AM", "start": "09:57:27 AM", "finish": "10:03:29 AM", "delay": "0:00:00", "occupancy": "362.29 seconds"}, "Consultation": {"arrival": "10:03:29 AM", "start": "10:03:29 AM", "finish": "10:17:34 AM", "delay": "0:00:00"}, "Billing": {"arrival": "10:17:34 AM", "start": "10:19:26 AM", "finish": "10:29:27 AM", "delay": "0:01:52.940171"}, "Pharmacy": {"arrival": "10:29:27 AM", "start": "10:29:27 AM", "finish": "10:44:29 AM", "delay": "0:00:00"}, "Dressing": {"arrival": "10:44:29 AM", "start": "11:54:08 AM", "finish": "12:09:10 PM", "delay": "1:09:38.772486"}}, "Patient 39": {"criticality": "Level 2", "Registration": {"arrival": "09:51:00 AM", "start": "09:51:00 AM", "finish": "09:58:03 AM", "delay": "0:00:00"}, "Bedspace Allocation": {"arrival": "09:58:03 AM", "start": "09:58:03 AM", "finish": "10:04:04 AM", "delay": "0:00:00", "occupancy": "360.50 seconds"}, "Scan": {"arrival": "10:04:04 AM", "start": "10:04:04 AM", "finish": "10:32:06 AM", "delay": "0:00:00"}}, "Patient 40": {"criticality": "Level 2", "Registration": {"arrival": "09:51:26 AM", "start": "09:51:26 AM", "finish": "09:58:29 AM", "delay": "0:00:00"}, "Bedspace Allocation": {"arrival": "09:58:29 AM", "start": "09:58:29 AM", "finish": "10:04:29 AM", "delay": "0:00:00", "occupancy": "360.16 seconds"}, "Consultation": {"arrival": "10:04:29 AM", "start": "10:04:29 AM", "finish": "10:18:32 AM", "delay": "0:00:00"}}, "Patient 41": {"criticality": "Level 3", "Registration": {"arrival": "09:51:50 AM", "start": "09:51:50 AM", "finish": "09:58:53 AM", "delay": "0:00:00"}, "Bedspace Allocation": {"arrival": "09:58:53 AM", "start": "09:58:53 AM", "finish": "10:04:56 AM", "delay": "0:00:00", "occupancy": "363.03 seconds"}, "Consultation": {"arrival": "10:04:56 AM", "start": "10:04:56 AM", "finish": "10:18:57 AM", "delay": "0:00:00"}, "Billing": {"arrival": "10:18:57 AM", "start": "10:22:08 AM", "finish": "10:32:11 AM", "delay": "0:03:11.114021"}, "Injection": {"arrival": "10:32:11 AM", "start": "10:44:13 AM", "finish": "10:55:15 AM", "delay": "0:12:02.369105"}}, "Patient 42": {"criticality": "Level 1", "Bedspace Allocation": {"arrival": "09:53:35 AM", "start": "09:53:35 AM", "finish": "09:59:38 AM", "delay": "0:00:00", "occupancy": "363.74 seconds"}, "Registration": {"arrival": "09:59:38 AM", "start": "09:59:38 AM", "finish": "10:06:42 AM", "delay": "0:00:00"}, "Billing": {"arrival": "10:56:14 AM", "start": "11:00:47 AM", "finish": "11:10:48 AM", "delay": "0:04:32.663113"}, "Xray": {"arrival": "10:21:09 AM", "start": "10:21:09 AM", "finish": "10:42:14 AM", "delay": "0:00:00"}, "Consultation": {"arrival": "10:42:14 AM", "start": "10:42:14 AM", "finish": "10:56:14 AM", "delay": "0:00:00"}, "Pharmacy": {"arrival": "11:10:48 AM", "start": "11:10:48 AM", "finish": "11:25:48 AM", "delay": "0:00:00"}}, "Patient 43": {"criticality": "Level 1", "Bedspace Allocation": {"arrival": "09:59:41 AM", "start": "09:59:41 AM", "finish": "10:05:43 AM", "delay": "0:00:00", "occupancy": "362.24 seconds"}, "Registration": {"arrival": "10:05:43 AM", "start": "10:05:43 AM", "finish": "10:12:44 AM", "delay": "0:00:00"}, "Consultation": {"arrival": "10:12:44 AM", "start": "10:12:44 AM", "finish": "10:26:47 AM", "delay": "0:00:00"}, "Billing": {"arrival": "10:26:47 AM", "start": "10:31:10 AM", "finish": "10:41:15 AM", "delay": "0:04:23.351629"}, "Injection": {"arrival": "10:41:15 AM", "start": "10:55:15 AM", "finish": "11:06:18 AM", "delay": "0:13:59.440589"}}, "Patient 44": {"criticality": "Level 1", "Bedspace Allocation": {"arrival": "10:03:05 AM", "start": "10:03:05 AM", "finish": "10:09:06 AM", "delay": "0:00:00", "occupancy": "361.36 seconds"}, "Registration": {"arrival": "10:09:06 AM", "start": "10:09:06 AM", "finish": "10:16:09 AM", "delay": "0:00:00"}, "Xray": {"arrival": "10:16:09 AM", "start": "10:16:09 AM", "finish": "10:37:13 AM", "delay": "0:00:00"}}, "Patient 45": {"criticality": "Level 2", "Registration": {"arrival": "10:07:28 AM", "start": "10:07:28 AM", "finish": "10:14:31 AM", "delay": "0:00:00"}, "Bedspace Allocation": {"arrival": "10:14:31 AM", "start": "10:14:31 AM", "finish": "10:20:33 AM", "delay": "0:00:00", "occupancy": "362.22 seconds"}, "Billing": {"arrival": "11:12:01 AM", "start": "11:12:01 AM", "finish": "11:22:02 AM", "delay": "0:00:00"}, "Xray": {"arrival": "10:36:57 AM", "start": "10:36:57 AM", "finish": "10:57:59 AM", "delay": "0:00:00"}, "Consultation": {"arrival": "10:57:59 AM", "start": "10:57:59 AM", "finish": "11:12:01 AM", "delay": "0:00:00"}, "Pharmacy": {"arrival": "11:22:02 AM", "start": "11:22:02 AM", "finish": "11:37:06 AM", "delay": "0:00:00"}}, "Patient 46": {"criticality": "Level 3", "Registration": {"arrival": "10:11:33 AM", "start": "10:11:33 AM", "finish": "10:18:36 AM", "delay": "0:00:00"}, "Bedspace Allocation": {"arrival": "10:18:36 AM", "start": "10:18:36 AM", "finish": "10:24:40 AM", "delay": "0:00:00", "occupancy": "363.61 seconds"}, "Consultation": {"arrival": "10:24:40 AM", "start": "10:24:40 AM", "finish": "10:38:43 AM", "delay": "0:00:00"}, "Billing": {"arrival": "10:38:43 AM", "start": "10:38:43 AM", "finish": "10:48:45 AM", "delay": "0:00:00"}, "Injection": {"arrival": "10:48:45 AM", "start": "11:06:18 AM", "finish": "11:17:20 AM", "delay": "0:17:33.143249"}}, "Patient 47": {"criticality": "Level 1", "Bedspace Allocation": {"arrival": "10:12:24 AM", "start": "10:12:24 AM", "finish": "10:18:25 AM", "delay": "0:00:00", "occupancy": "361.83 seconds"}, "Registration": {"arrival": "10:18:25 AM", "start": "10:18:25 AM", "finish": "10:25:27 AM", "delay": "0:00:00"}, "Scan": {"arrival": "10:25:27 AM", "start": "10:25:27 AM", "finish": "10:53:28 AM", "delay": "0:00:00"}}, "Patient 48": {"criticality": "Level 3", "Registration": {"arrival": "10:12:50 AM", "start": "10:12:50 AM", "finish": "10:19:52 AM", "delay": "0:00:00"}, "Bedspace Allocation": {"arrival": "10:19:52 AM", "start": "10:19:52 AM", "finish": "10:25:54 AM", "delay": "0:00:00", "occupancy": "361.83 seconds"}, "Consultation": {"arrival": "10:25:54 AM", "start": "10:25:54 AM", "finish": "10:39:55 AM", "delay": "0:00:00"}, "Billing": {"arrival": "10:39:55 AM", "start": "10:39:55 AM", "finish": "10:49:56 AM", "delay": "0:00:00"}, "Pharmacy": {"arrival": "10:49:56 AM", "start": "10:49:56 AM", "finish": "11:04:57 AM", "delay": "0:00:00"}, "Dressing": {"arrival": "11:04:57 AM", "start": "12:09:10 PM", "finish": "12:24:10 PM", "delay": "1:04:13.062661"}}, "Patient 49": {"criticality": "Level 3", "Registration": {"arrival": "10:16:31 AM", "start": "10:16:31 AM", "finish": "10:23:32 AM", "delay": "0:00:00"}, "Bedspace Allocation": {"arrival": "10:23:32 AM", "start": "10:23:32 AM", "finish": "10:29:35 AM", "delay": "0:00:00", "occupancy": "363.66 seconds"}, "Consultation": {"arrival": "10:29:35 AM", "start": "10:29:35 AM", "finish": "10:43:40 AM", "delay": "0:00:00"}}, "Patient 50": {"criticality": "Level 1", "Bedspace Allocation": {"arrival": "10:17:30 AM", "start": "10:17:30 AM", "finish": "10:23:32 AM", "delay": "0:00:00", "occupancy": "362.37 seconds"}, "Registration": {"arrival": "10:23:32 AM", "start": "10:23:32 AM", "finish": "10:30:34 AM", "delay": "0:00:00"}, "Consultation": {"arrival": "10:30:34 AM", "start": "10:30:34 AM", "finish": "10:44:39 AM", "delay": "0:00:00"}, "Billing": {"arrival": "10:44:39 AM", "start": "10:44:39 AM", "finish": "10:54:41 AM", "delay": "0:00:00"}, "Xray": {"arrival": "10:54:41 AM", "start": "10:57:59 AM", "finish": "11:19:03 AM", "delay": "0:03:17.646429"}}, "Patient 51": {"criticality": "Level 3", "Registration": {"arrival": "10:24:51 AM", "start": "10:24:51 AM", "finish": "10:31:55 AM", "delay": "0:00:00"}, "Bedspace Allocation": {"arrival": "10:31:55 AM", "start": "10:31:55 AM", "finish": "10:37:58 AM", "delay": "0:00:00", "occupancy": "363.53 seconds"}, "Consultation": {"arrival": "10:37:58 AM", "start": "10:37:58 AM", "finish": "10:52:02 AM", "delay": "0:00:00"}, "Billing": {"arrival": "10:52:02 AM", "start": "10:54:41 AM", "finish": "11:04:43 AM", "delay": "0:02:39.063240"}, "Xray": {"arrival": "11:04:43 AM", "start": "11:04:59 AM", "finish": "11:25:59 AM", "delay": "0:00:15.459878"}}, "Patient 52": {"criticality": "Level 2", "Registration": {"arrival": "10:26:58 AM", "start": "10:26:58 AM", "finish": "10:34:00 AM", "delay": "0:00:00"}, "Bedspace Allocation": {"arrival": "10:34:00 AM", "start": "10:34:00 AM", "finish": "10:40:01 AM", "delay": "0:00:00", "occupancy": "360.90 seconds"}, "Consultation": {"arrival": "10:40:01 AM", "start": "10:40:01 AM", "finish": "10:54:03 AM", "delay": "0:00:00"}, "Billing": {"arrival": "10:54:03 AM", "start": "10:58:49 AM", "finish": "11:08:52 AM", "delay": "0:04:45.901463"}, "Pharmacy": {"arrival": "11:08:52 AM", "start": "11:08:52 AM", "finish": "11:23:54 AM", "delay": "0:00:00"}, "Dressing": {"arrival": "11:23:54 AM", "start": "12:24:10 PM", "finish": "12:39:13 PM", "delay": "1:00:15.223084"}}, "Patient 53": {"criticality": "Level 1", "Bedspace Allocation": {"arrival": "10:28:53 AM", "start": "10:28:53 AM", "finish": "10:34:55 AM", "delay": "0:00:00", "occupancy": "362.98 seconds"}, "Registration": {"arrival": "10:34:55 AM", "start": "10:34:55 AM", "finish": "10:41:59 AM", "delay": "0:00:00"}, "Billing": {"arrival": "11:27:06 AM", "start": "11:34:06 AM", "finish": "11:44:11 AM", "delay": "0:07:00.880837"}, "Xray": {"arrival": "10:52:01 AM", "start": "10:52:01 AM", "finish": "11:13:05 AM", "delay": "0:00:00"}, "Consultation": {"arrival": "11:13:05 AM", "start": "11:13:05 AM", "finish": "11:27:06 AM", "delay": "0:00:00"}, "Pharmacy": {"arrival": "11:44:11 AM", "start": "11:44:11 AM", "finish": "11:59:14 AM", "delay": "0:00:00"}}, "Patient 54": {"criticality": "Level 2", "Registration": {"arrival": "10:29:03 AM", "start": "10:29:03 AM", "finish": "10:36:06 AM", "delay": "0:00:00"}, "Bedspace Allocation": {"arrival": "10:36:06 AM", "start": "10:36:06 AM", "finish": "10:42:08 AM", "delay": "0:00:00", "occupancy": "362.58 seconds"}, "Xray": {"arrival": "10:42:08 AM", "start": "10:42:08 AM", "finish": "11:03:09 AM", "delay": "0:00:00"}}, "Patient 55": {"criticality": "Level 3", "Registration": {"arrival": "10:30:51 AM", "start": "10:30:51 AM", "finish": "10:37:51 AM", "delay": "0:00:00"}, "Bedspace Allocation": {"arrival": "10:37:51 AM", "start": "10:37:51 AM", "finish": "10:43:55 AM", "delay": "0:00:00", "occupancy": "363.30 seconds"}, "Xray": {"arrival": "10:43:55 AM", "start": "10:43:55 AM", "finish": "11:04:59 AM", "delay": "0:00:00"}}, "Patient 56": {"criticality": "Level 3", "Registration": {"arrival": "10:37:35 AM", "start": "10:37:35 AM", "finish": "10:44:39 AM", "delay": "0:00:00"}, "Bedspace Allocation": {"arrival": "10:44:39 AM", "start": "10:44:39 AM", "finish": "10:50:43 AM", "delay": "0:00:00", "occupancy": "364.06 seconds"}, "Billing": {"arrival": "11:24:13 AM", "start": "11:24:13 AM", "finish": "11:34:15 AM", "delay": "0:00:00"}, "Xray": {"arrival": "11:00:47 AM", "start": "11:03:09 AM", "finish": "11:24:13 AM", "delay": "0:02:22.447650"}, "Pharmacy": {"arrival": "11:34:15 AM", "start": "11:34:15 AM", "finish": "11:49:19 AM", "delay": "0:00:00"}}, "Patient 57": {"criticality": "Level 3", "Registration": {"arrival": "10:37:56 AM", "start": "10:37:56 AM", "finish": "10:45:00 AM", "delay": "0:00:00"}, "Bedspace Allocation": {"arrival": "10:45:00 AM", "start": "10:45:00 AM", "finish": "10:51:03 AM", "delay": "0:00:00", "occupancy": "362.96 seconds"}, "Billing": {"arrival": "10:51:03 AM", "start": "10:52:01 AM", "finish": "11:02:05 AM", "delay": "0:00:58.285027"}, "Scan": {"arrival": "11:02:05 AM", "start": "11:02:05 AM", "finish": "11:30:08 AM", "delay": "0:00:00"}}, "Patient 58": {"criticality": "Level 3", "Registration": {"arrival": "10:55:20 AM", "start": "10:55:20 AM", "finish": "11:02:21 AM", "delay": "0:00:00"}, "Bedspace Allocation": {"arrival": "11:02:21 AM", "start": "11:02:21 AM", "finish": "11:08:25 AM", "delay": "0:00:00", "occupancy": "363.95 seconds"}, "Consultation": {"arrival": "11:53:32 AM", "start": "11:53:32 AM", "finish": "12:07:36 PM", "delay": "0:00:00"}, "Billing": {"arrival": "11:22:28 AM", "start": "11:22:28 AM", "finish": "11:32:30 AM", "delay": "0:00:00"}, "Xray": {"arrival": "11:32:30 AM", "start": "11:32:30 AM", "finish": "11:53:32 AM", "delay": "0:00:00"}}, "Patient 59": {"criticality": "Level 2", "Registration": {"arrival": "10:56:53 AM", "start": "10:56:53 AM", "finish": "11:03:55 AM", "delay": "0:00:00"}, "Bedspace Allocation": {"arrival": "11:03:55 AM", "start": "11:03:55 AM", "finish": "11:09:59 AM", "delay": "0:00:00", "occupancy": "363.86 seconds"}, "Consultation": {"arrival": "11:09:59 AM", "start": "11:09:59 AM", "finish": "11:24:03 AM", "delay": "0:00:00"}, "Billing": {"arrival": "11:24:03 AM", "start": "11:24:03 AM", "finish": "11:34:06 AM", "delay": "0:00:00"}, "Xray": {"arrival": "11:34:06 AM", "start": "11:34:06 AM", "finish": "11:55:10 AM", "delay": "0:00:00"}}, "Patient 60": {"criticality": "Level 1", "Bedspace Allocation": {"arrival": "10:57:43 AM", "start": "10:57:43 AM", "finish": "11:03:47 AM", "delay": "0:00:00", "occupancy": "364.94 seconds"}, "Registration": {"arrival": "11:03:47 AM", "start": "11:03:47 AM", "finish": "11:10:47 AM", "delay": "0:00:00"}, "Consultation": {"arrival": "12:06:40 PM", "start": "12:06:40 PM", "finish": "12:20:41 PM", "delay": "0:00:00"}, "Billing": {"arrival": "12:20:41 PM", "start": "12:20:41 PM", "finish": "12:30:46 PM", "delay": "0:00:00"}, "Xray": {"arrival": "11:34:50 AM", "start": "11:45:38 AM", "finish": "12:06:40 PM", "delay": "0:10:47.949221"}, "Pharmacy": {"arrival": "12:30:46 PM", "start": "12:30:46 PM", "finish": "12:45:46 PM", "delay": "0:00:00"}}, "Patient 61": {"criticality": "Level 3", "Registration": {"arrival": "11:10:55 AM", "start": "11:10:55 AM", "finish": "11:17:59 AM", "delay": "0:00:00"}, "Bedspace Allocation": {"arrival": "11:17:59 AM", "start": "11:17:59 AM", "finish": "11:24:00 AM", "delay": "0:00:00", "occupancy": "361.35 seconds"}, "Consultation": {"arrival": "11:24:00 AM", "start": "11:24:00 AM", "finish": "11:38:03 AM", "delay": "0:00:00"}, "Billing": {"arrival": "11:38:03 AM", "start": "11:38:03 AM", "finish": "11:48:06 AM", "delay": "0:00:00"}, "Pharmacy": {"arrival": "11:48:06 AM", "start": "11:48:06 AM", "finish": "12:03:07 PM", "delay": "0:00:00"}}, "Patient 62": {"criticality": "Level 3", "Registration": {"arrival": "11:11:32 AM", "start": "11:11:32 AM", "finish": "11:18:33 AM", "delay": "0:00:00"}, "Bedspace Allocation": {"arrival": "11:18:33 AM", "start": "11:18:33 AM", "finish": "11:24:37 AM", "delay": "0:00:00", "occupancy": "364.18 seconds"}, "Xray": {"arrival": "11:24:37 AM", "start": "11:24:37 AM", "finish": "11:45:38 AM", "delay": "0:00:00"}}, "Patient 63": {"criticality": "Level 3", "Registration": {"arrival": "11:13:53 AM", "start": "11:13:53 AM", "finish": "11:20:57 AM", "delay": "0:00:00"}, "Bedspace Allocation": {"arrival": "11:20:57 AM", "start": "11:20:57 AM", "finish": "11:27:00 AM", "delay": "0:00:00", "occupancy": "362.99 seconds"}, "Billing": {"arrival": "11:27:00 AM", "start": "11:32:30 AM", "finish": "11:42:34 AM", "delay": "0:05:30.043139"}, "Xray": {"arrival": "11:42:34 AM", "start": "11:50:24 AM", "finish": "12:11:28 PM", "delay": "0:07:50.256017"}}, "Patient 64": {"criticality": "Level 2", "Registration": {"arrival": "11:15:16 AM", "start": "11:15:16 AM", "finish": "11:22:19 AM", "delay": "0:00:00"}, "Bedspace Allocation": {"arrival": "11:22:19 AM", "start": "11:22:19 AM", "finish": "11:28:22 AM", "delay": "0:00:00", "occupancy": "363.00 seconds"}, "Billing": {"arrival": "11:28:22 AM", "start": "11:34:15 AM", "finish": "11:44:18 AM", "delay": "0:05:52.836568"}, "Scan": {"arrival": "11:44:18 AM", "start": "11:44:18 AM", "finish": "12:12:20 PM", "delay": "0:00:00"}}, "Patient 65": {"criticality": "Level 1", "Bedspace Allocation": {"arrival": "11:16:18 AM", "start": "11:16:18 AM", "finish": "11:22:19 AM", "delay": "0:00:00", "occupancy": "361.41 seconds"}, "Registration": {"arrival": "11:22:19 AM", "start": "11:22:19 AM", "finish": "11:29:22 AM", "delay": "0:00:00"}, "Xray": {"arrival": "11:29:22 AM", "start": "11:29:22 AM", "finish": "11:50:24 AM", "delay": "0:00:00"}}, "Patient 66": {"criticality": "Level 2", "Registration": {"arrival": "11:17:56 AM", "start": "11:17:56 AM", "finish": "11:24:57 AM", "delay": "0:00:00"}, "Bedspace Allocation": {"arrival": "11:24:57 AM", "start": "11:24:57 AM", "finish": "11:31:00 AM", "delay": "0:00:00", "occupancy": "362.99 seconds"}, "Consultation": {"arrival": "11:31:00 AM", "start": "11:31:00 AM", "finish": "11:45:02 AM", "delay": "0:00:00"}, "Billing": {"arrival": "11:45:02 AM", "start": "11:45:02 AM", "finish": "11:55:04 AM", "delay": "0:00:00"}, "Injection": {"arrival": "11:55:04 AM", "start": "11:55:04 AM", "finish": "12:06:07 PM", "delay": "0:00:00"}}, "Patient 67": {"criticality": "Level 3", "Registration": {"arrival": "11:18:08 AM", "start": "11:18:08 AM", "finish": "11:25:10 AM", "delay": "0:00:00"}, "Bedspace Allocation": {"arrival": "11:25:10 AM", "start": "11:25:10 AM", "finish": "11:31:13 AM", "delay": "0:00:00", "occupancy": "363.76 seconds"}}, "Patient 68": {"criticality": "Level 2", "Registration": {"arrival": "11:24:56 AM", "start": "11:24:56 AM", "finish": "11:31:56 AM", "delay": "0:00:00"}, "Bedspace Allocation": {"arrival": "11:31:56 AM", "start": "11:31:56 AM", "finish": "11:37:57 AM", "delay": "0:00:00", "occupancy": "360.22 seconds"}, "Consultation": {"arrival": "11:37:57 AM", "start": "11:37:57 AM", "finish": "11:51:57 AM", "delay": "0:00:00"}, "Billing": {"arrival": "11:51:57 AM", "start": "11:51:57 AM", "finish": "12:02:02 PM", "delay": "0:00:00"}, "Pharmacy": {"arrival": "12:02:02 PM", "start": "12:02:02 PM", "finish": "12:17:03 PM", "delay": "0:00:00"}}, "Patient 69": {"criticality": "Level 1", "Bedspace Allocation": {"arrival": "11:32:09 AM", "start": "11:32:09 AM", "finish": "11:38:11 AM", "delay": "0:00:00", "occupancy": "362.59 seconds"}, "Registration": {"arrival": "11:38:11 AM", "start": "11:38:11 AM", "finish": "11:45:13 AM", "delay": "0:00:00"}, "Billing": {"arrival": "11:45:13 AM", "start": "11:45:13 AM", "finish": "11:55:16 AM", "delay": "0:00:00"}, "Scan": {"arrival": "11:55:16 AM", "start": "11:55:16 AM", "finish": "12:23:19 PM", "delay": "0:00:00"}}, "Patient 70": {"criticality": "Level 2", "Registration": {"arrival": "11:35:39 AM", "start": "11:35:39 AM", "finish": "11:42:43 AM", "delay": "0:00:00"}, "Bedspace Allocation": {"arrival": "11:42:43 AM", "start": "11:42:43 AM", "finish": "11:48:46 AM", "delay": "0:00:00", "occupancy": "363.52 seconds"}, "Consultation": {"arrival": "12:33:55 PM", "start": "12:33:55 PM", "finish": "12:47:59 PM", "delay": "0:00:00"}, "Billing": {"arrival": "12:47:59 PM", "start": "12:47:59 PM", "finish": "12:58:01 PM", "delay": "0:00:00"}, "Xray": {"arrival": "12:12:51 PM", "start": "12:12:51 PM", "finish": "12:33:55 PM", "delay": "0:00:00"}, "Pharmacy": {"arrival": "12:58:01 PM", "start": "12:58:01 PM", "finish": "13:13:03 PM", "delay": "0:00:00"}}, "Patient 71": {"criticality": "Level 2", "Registration": {"arrival": "11:35:48 AM", "start": "11:35:48 AM", "finish": "11:42:50 AM", "delay": "0:00:00"}, "Bedspace Allocation": {"arrival": "11:42:50 AM", "start": "11:42:50 AM", "finish": "11:48:53 AM", "delay": "0:00:00", "occupancy": "363.28 seconds"}, "Consultation": {"arrival": "11:48:53 AM", "start": "11:48:53 AM", "finish": "12:02:54 PM", "delay": "0:00:00"}, "Billing": {"arrival": "12:02:54 PM", "start": "12:02:54 PM", "finish": "12:12:57 PM", "delay": "0:00:00"}, "Injection": {"arrival": "12:12:57 PM", "start": "12:12:57 PM", "finish": "12:23:59 PM", "delay": "0:00:00"}}, "Patient 72": {"criticality": "Level 2", "Registration": {"arrival": "11:37:56 AM", "start": "11:37:56 AM", "finish": "11:45:00 AM", "delay": "0:00:00"}, "Bedspace Allocation": {"arrival": "11:45:00 AM", "start": "11:45:00 AM", "finish": "11:51:01 AM", "delay": "0:00:00", "occupancy": "360.61 seconds"}, "Consultation": {"arrival": "11:51:01 AM", "start": "11:51:01 AM", "finish": "12:05:02 PM", "delay": "0:00:00"}, "Billing": {"arrival": "12:36:07 PM", "start": "12:36:07 PM", "finish": "12:46:12 PM", "delay": "0:00:00"}, "Xray": {"arrival": "12:15:05 PM", "start": "12:15:05 PM", "finish": "12:36:07 PM", "delay": "0:00:00"}, "Pharmacy": {"arrival": "12:46:12 PM", "start": "12:46:12 PM", "finish": "13:01:16 PM", "delay": "0:00:00"}, "Dressing": {"arrival": "13:01:16 PM", "start": "13:01:16 PM", "finish": "13:16:17 PM", "delay": "0:00:00"}}, "Patient 73": {"criticality": "Level 3", "Registration": {"arrival": "11:41:16 AM", "start": "11:41:16 AM", "finish": "11:48:20 AM", "delay": "0:00:00"}, "Bedspace Allocation": {"arrival": "11:48:20 AM", "start": "11:48:20 AM", "finish": "11:54:23 AM", "delay": "0:00:00", "occupancy": "363.32 seconds"}, "Consultation": {"arrival": "11:54:23 AM", "start": "11:54:23 AM", "finish": "12:08:26 PM", "delay": "0:00:00"}, "Billing": {"arrival": "12:08:26 PM", "start": "12:08:26 PM", "finish": "12:18:27 PM", "delay": "0:00:00"}, "Pharmacy": {"arrival": "12:18:27 PM", "start": "12:18:27 PM", "finish": "12:33:28 PM", "delay": "0:00:00"}}, "Patient 74": {"criticality": "Level 2", "Registration": {"arrival": "11:42:33 AM", "start": "11:42:43 AM", "finish": "11:49:44 AM", "delay": "0:00:10.422318"}, "Bedspace Allocation": {"arrival": "11:49:44 AM", "start": "11:49:44 AM", "finish": "11:55:46 AM", "delay": "0:00:00", "occupancy": "361.56 seconds"}, "Xray": {"arrival": "11:55:46 AM", "start": "11:55:46 AM", "finish": "12:16:50 PM", "delay": "0:00:00"}}, "Patient 75": {"criticality": "Level 1", "Bedspace Allocation": {"arrival": "11:47:54 AM", "start": "11:47:54 AM", "finish": "11:53:55 AM", "delay": "0:00:00", "occupancy": "361.35 seconds"}, "Registration": {"arrival": "11:53:55 AM", "start": "11:53:55 AM", "finish": "12:00:59 PM", "delay": "0:00:00"}, "Consultation": {"arrival": "12:00:59 PM", "start": "12:00:59 PM", "finish": "12:15:01 PM", "delay": "0:00:00"}, "Billing": {"arrival": "12:15:01 PM", "start": "12:15:01 PM", "finish": "12:25:04 PM", "delay": "0:00:00"}, "Pharmacy": {"arrival": "12:25:04 PM", "start": "12:25:04 PM", "finish": "12:40:08 PM", "delay": "0:00:00"}}, "Patient 76": {"criticality": "Level 2", "Registration": {"arrival": "11:48:19 AM", "start": "11:48:19 AM", "finish": "11:55:22 AM", "delay": "0:00:00"}, "Bedspace Allocation": {"arrival": "11:55:22 AM", "start": "11:55:22 AM", "finish": "12:01:25 PM", "delay": "0:00:00", "occupancy": "363.24 seconds"}}, "Patient 77": {"criticality": "Level 3", "Registration": {"arrival": "11:49:46 AM", "start": "11:49:46 AM", "finish": "11:56:48 AM", "delay": "0:00:00"}, "Bedspace Allocation": {"arrival": "11:56:48 AM", "start": "11:56:48 AM", "finish": "12:02:49 PM", "delay": "0:00:00", "occupancy": "361.17 seconds"}, "Consultation": {"arrival": "12:02:49 PM", "start": "12:02:49 PM", "finish": "12:16:52 PM", "delay": "0:00:00"}, "Billing": {"arrival": "12:16:52 PM", "start": "12:16:52 PM", "finish": "12:26:52 PM", "delay": "0:00:00"}, "Xray": {"arrival": "12:26:52 PM", "start": "12:26:52 PM", "finish": "12:47:55 PM", "delay": "0:00:00"}}, "Patient 78": {"criticality": "Level 3", "Registration": {"arrival": "11:56:00 AM", "start": "11:56:00 AM", "finish": "12:03:00 PM", "delay": "0:00:00"}, "Bedspace Allocation": {"arrival": "12:03:00 PM", "start": "12:03:00 PM", "finish": "12:09:04 PM", "delay": "0:00:00", "occupancy": "364.12 seconds"}, "Consultation": {"arrival": "12:09:04 PM", "start": "12:09:04 PM", "finish": "12:23:04 PM", "delay": "0:00:00"}, "Billing": {"arrival": "12:23:04 PM", "start": "12:24:24 PM", "finish": "12:34:26 PM", "delay": "0:01:19.446657"}, "Pharmacy": {"arrival": "12:34:26 PM", "start": "12:34:26 PM", "finish": "12:49:31 PM", "delay": "0:00:00"}}, "Patient 79": {"criticality": "Level 2", "Registration": {"arrival": "12:00:28 PM", "start": "12:00:28 PM", "finish": "12:07:30 PM", "delay": "0:00:00"}, "Bedspace Allocation": {"arrival": "12:07:30 PM", "start": "12:07:30 PM", "finish": "12:13:34 PM", "delay": "0:00:00", "occupancy": "363.97 seconds"}}, "Patient 80": {"criticality": "Level 3", "Registration": {"arrival": "12:01:15 PM", "start": "12:01:15 PM", "finish": "12:08:18 PM", "delay": "0:00:00"}, "Bedspace Allocation": {"arrival": "12:08:18 PM", "start": "12:08:18 PM", "finish": "12:14:21 PM", "delay": "0:00:00", "occupancy": "362.56 seconds"}, "Billing": {"arrival": "12:59:27 PM", "start": "12:59:27 PM", "finish": "13:09:28 PM", "delay": "0:00:00"}, "Xray": {"arrival": "12:24:24 PM", "start": "12:24:24 PM", "finish": "12:45:25 PM", "delay": "0:00:00"}, "Consultation": {"arrival": "12:45:25 PM", "start": "12:45:25 PM", "finish": "12:59:27 PM", "delay": "0:00:00"}, "Pharmacy": {"arrival": "13:09:28 PM", "start": "13:09:28 PM", "finish": "13:24:30 PM", "delay": "0:00:00"}}, "Patient 81": {"criticality": "Level 1", "Bedspace Allocation": {"arrival": "12:07:46 PM", "start": "12:07:46 PM", "finish": "12:13:46 PM", "delay": "0:00:00", "occupancy": "360.50 seconds"}, "Registration": {"arrival": "12:13:46 PM", "start": "12:13:46 PM", "finish": "12:20:49 PM", "delay": "0:00:00"}, "Consultation": {"arrival": "12:20:49 PM", "start": "12:20:49 PM", "finish": "12:34:53 PM", "delay": "0:00:00"}}, "Patient 82": {"criticality": "Level 2", "Registration": {"arrival": "12:10:05 PM", "start": "12:10:05 PM", "finish": "12:17:05 PM", "delay": "0:00:00"}, "Bedspace Allocation": {"arrival": "12:17:05 PM", "start": "12:17:05 PM", "finish": "12:23:07 PM", "delay": "0:00:00", "occupancy": "361.09 seconds"}, "Consultation": {"arrival": "12:23:07 PM", "start": "12:23:07 PM", "finish": "12:37:07 PM", "delay": "0:00:00"}, "Billing": {"arrival": "12:37:07 PM", "start": "12:37:07 PM", "finish": "12:47:10 PM", "delay": "0:00:00"}, "Pharmacy": {"arrival": "12:47:10 PM", "start": "12:47:10 PM", "finish": "13:02:13 PM", "delay": "0:00:00"}}, "Patient 83": {"criticality": "Level 2", "Registration": {"arrival": "12:17:24 PM", "start": "12:17:24 PM", "finish": "12:24:28 PM", "delay": "0:00:00"}, "Bedspace Allocation": {"arrival": "12:24:28 PM", "start": "12:24:28 PM", "finish": "12:30:32 PM", "delay": "0:00:00", "occupancy": "364.14 seconds"}, "Consultation": {"arrival": "13:15:41 PM", "start": "13:15:41 PM", "finish": "13:29:43 PM", "delay": "0:00:00"}, "Billing": {"arrival": "12:44:36 PM", "start": "12:44:36 PM", "finish": "12:54:40 PM", "delay": "0:00:00"}, "Xray": {"arrival": "12:54:40 PM", "start": "12:54:40 PM", "finish": "13:15:41 PM", "delay": "0:00:00"}}, "Patient 84": {"criticality": "Level 2", "Registration": {"arrival": "12:23:50 PM", "start": "12:23:50 PM", "finish": "12:30:54 PM", "delay": "0:00:00"}, "Bedspace Allocation": {"arrival": "12:30:54 PM", "start": "12:30:54 PM", "finish": "12:36:57 PM", "delay": "0:00:00", "occupancy": "363.22 seconds"}, "Consultation": {"arrival": "12:36:57 PM", "start": "12:36:57 PM", "finish": "12:51:00 PM", "delay": "0:00:00"}, "Billing": {"arrival": "13:22:04 PM", "start": "13:29:51 PM", "finish": "13:39:53 PM", "delay": "0:07:46.914961"}, "Xray": {"arrival": "13:01:03 PM", "start": "13:01:03 PM", "finish": "13:22:04 PM", "delay": "0:00:00"}, "Pharmacy": {"arrival": "13:39:53 PM", "start": "13:39:53 PM", "finish": "13:54:56 PM", "delay": "0:00:00"}, "Dressing": {"arrival": "13:54:56 PM", "start": "13:54:56 PM", "finish": "14:09:58 PM", "delay": "0:00:00"}}, "Patient 85": {"criticality": "Level 3", "Registration": {"arrival": "12:24:56 PM", "start": "12:24:56 PM", "finish": "12:31:58 PM", "delay": "0:00:00"}, "Bedspace Allocation": {"arrival": "12:31:58 PM", "start": "12:31:58 PM", "finish": "12:38:02 PM", "delay": "0:00:00", "occupancy": "363.08 seconds"}, "Consultation": {"arrival": "13:29:42 PM", "start": "13:29:42 PM", "finish": "13:43:47 PM", "delay": "0:00:00"}, "Billing": {"arrival": "13:43:47 PM", "start": "13:43:47 PM", "finish": "13:53:49 PM", "delay": "0:00:00"}, "Xray": {"arrival": "13:02:05 PM", "start": "13:08:40 PM", "finish": "13:29:42 PM", "delay": "0:06:34.405103"}, "Pharmacy": {"arrival": "13:53:49 PM", "start": "13:55:27 PM", "finish": "14:10:31 PM", "delay": "0:01:37.341724"}}, "Patient 86": {"criticality": "Level 3", "Registration": {"arrival": "12:34:35 PM", "start": "12:34:35 PM", "finish": "12:41:37 PM", "delay": "0:00:00"}, "Bedspace Allocation": {"arrival": "12:41:37 PM", "start": "12:41:37 PM", "finish": "12:47:38 PM", "delay": "0:00:00", "occupancy": "361.09 seconds"}, "Xray": {"arrival": "12:47:38 PM", "start": "12:47:38 PM", "finish": "13:08:40 PM", "delay": "0:00:00"}}, "Patient 87": {"criticality": "Level 1", "Bedspace Allocation": {"arrival": "12:39:52 PM", "start": "12:39:52 PM", "finish": "12:45:55 PM", "delay": "0:00:00", "occupancy": "363.13 seconds"}, "Registration": {"arrival": "12:45:55 PM", "start": "12:45:55 PM", "finish": "12:52:58 PM", "delay": "0:00:00"}, "Xray": {"arrival": "12:52:58 PM", "start": "12:52:58 PM", "finish": "13:14:00 PM", "delay": "0:00:00"}}, "Patient 88": {"criticality": "Level 3", "Registration": {"arrival": "12:45:22 PM", "start": "12:45:22 PM", "finish": "12:52:23 PM", "delay": "0:00:00"}, "Bedspace Allocation": {"arrival": "12:52:23 PM", "start": "12:52:23 PM", "finish": "12:58:25 PM", "delay": "0:00:00", "occupancy": "361.96 seconds"}, "Consultation": {"arrival": "12:58:25 PM", "start": "12:58:25 PM", "finish": "13:12:29 PM", "delay": "0:00:00"}, "Billing": {"arrival": "13:12:29 PM", "start": "13:12:29 PM", "finish": "13:22:31 PM", "delay": "0:00:00"}, "Scan": {"arrival": "13:22:31 PM", "start": "13:22:31 PM", "finish": "13:50:35 PM", "delay": "0:00:00"}}, "Patient 89": {"criticality": "Level 1", "Bedspace Allocation": {"arrival": "12:49:36 PM", "start": "12:49:36 PM", "finish": "12:55:38 PM", "delay": "0:00:00", "occupancy": "362.17 seconds"}, "Registration": {"arrival": "12:55:38 PM", "start": "12:55:38 PM", "finish": "13:02:38 PM", "delay": "0:00:00"}, "Scan": {"arrival": "13:02:38 PM", "start": "13:02:38 PM", "finish": "13:30:42 PM", "delay": "0:00:00"}}, "Patient 90": {"criticality": "Level 1", "Bedspace Allocation": {"arrival": "12:52:38 PM", "start": "12:52:38 PM", "finish": "12:58:39 PM", "delay": "0:00:00", "occupancy": "361.10 seconds"}, "Registration": {"arrival": "12:58:39 PM", "start": "12:58:39 PM", "finish": "13:05:43 PM", "delay": "0:00:00"}, "Consultation": {"arrival": "13:50:56 PM", "start": "13:50:56 PM", "finish": "14:04:57 PM", "delay": "0:00:00"}, "Billing": {"arrival": "14:04:57 PM", "start": "14:04:57 PM", "finish": "14:14:59 PM", "delay": "0:00:00"}, "Xray": {"arrival": "13:29:51 PM", "start": "13:29:51 PM", "finish": "13:50:56 PM", "delay": "0:00:00"}, "Pharmacy": {"arrival": "14:14:59 PM", "start": "14:14:59 PM", "finish": "14:30:03 PM", "delay": "0:00:00"}, "Dressing": {"arrival": "14:30:03 PM", "start": "14:30:03 PM", "finish": "14:45:03 PM", "delay": "0:00:00"}}, "Patient 91": {"criticality": "Level 1", "Bedspace Allocation": {"arrival": "12:54:00 PM", "start": "12:54:00 PM", "finish": "13:00:04 PM", "delay": "0:00:00", "occupancy": "364.48 seconds"}, "Registration": {"arrival": "13:00:04 PM", "start": "13:00:04 PM", "finish": "13:07:07 PM", "delay": "0:00:00"}, "Consultation": {"arrival": "13:07:07 PM", "start": "13:07:07 PM", "finish": "13:21:10 PM", "delay": "0:00:00"}, "Billing": {"arrival": "13:21:10 PM", "start": "13:22:31 PM", "finish": "13:32:36 PM", "delay": "0:01:20.712584"}, "Pharmacy": {"arrival": "13:32:36 PM", "start": "13:32:36 PM", "finish": "13:47:40 PM", "delay": "0:00:00"}}, "Patient 92": {"criticality": "Level 2", "Registration": {"arrival": "12:54:02 PM", "start": "12:54:02 PM", "finish": "13:01:06 PM", "delay": "0:00:00"}, "Bedspace Allocation": {"arrival": "13:01:06 PM", "start": "13:01:06 PM", "finish": "13:07:10 PM", "delay": "0:00:00", "occupancy": "363.54 seconds"}, "Scan": {"arrival": "13:07:10 PM", "start": "13:07:10 PM", "finish": "13:35:10 PM", "delay": "0:00:00"}}, "Patient 93": {"criticality": "Level 1", "Bedspace Allocation": {"arrival": "12:54:55 PM", "start": "12:54:55 PM", "finish": "13:00:57 PM", "delay": "0:00:00", "occupancy": "362.91 seconds"}, "Registration": {"arrival": "13:00:57 PM", "start": "13:00:57 PM", "finish": "13:08:00 PM", "delay": "0:00:00"}, "Consultation": {"arrival": "13:08:00 PM", "start": "13:08:00 PM", "finish": "13:22:05 PM", "delay": "0:00:00"}, "Billing": {"arrival": "13:22:05 PM", "start": "13:30:19 PM", "finish": "13:40:22 PM", "delay": "0:08:13.871962"}, "Pharmacy": {"arrival": "13:40:22 PM", "start": "13:40:22 PM", "finish": "13:55:27 PM", "delay": "0:00:00"}}, "Patient 94": {"criticality": "Level 2", "Registration": {"arrival": "13:01:26 PM", "start": "13:01:26 PM", "finish": "13:08:26 PM", "delay": "0:00:00"}, "Bedspace Allocation": {"arrival": "13:08:26 PM", "start": "13:08:26 PM", "finish": "13:14:31 PM", "delay": "0:00:00", "occupancy": "364.56 seconds"}, "Consultation": {"arrival": "13:14:31 PM", "start": "13:14:31 PM", "finish": "13:28:35 PM", "delay": "0:00:00"}, "Billing": {"arrival": "13:28:35 PM", "start": "13:31:01 PM", "finish": "13:41:01 PM", "delay": "0:02:26.165905"}, "Pharmacy": {"arrival": "13:41:01 PM", "start": "13:41:01 PM", "finish": "13:56:02 PM", "delay": "0:00:00"}}, "Patient 95": {"criticality": "Level 1", "Bedspace Allocation": {"arrival": "13:02:10 PM", "start": "13:02:10 PM", "finish": "13:08:11 PM", "delay": "0:00:00", "occupancy": "361.91 seconds"}, "Registration": {"arrival": "13:08:11 PM", "start": "13:08:11 PM", "finish": "13:15:14 PM", "delay": "0:00:00"}, "Consultation": {"arrival": "13:15:14 PM", "start": "13:15:14 PM", "finish": "13:29:14 PM", "delay": "0:00:00"}, "Billing": {"arrival": "13:29:14 PM", "start": "13:32:36 PM", "finish": "13:42:40 PM", "delay": "0:03:21.849799"}, "Pharmacy": {"arrival": "13:42:40 PM", "start": "13:47:40 PM", "finish": "14:02:44 PM", "delay": "0:04:59.747401"}}, "Patient 96": {"criticality": "Level 2", "Registration": {"arrival": "13:02:44 PM", "start": "13:02:44 PM", "finish": "13:09:48 PM", "delay": "0:00:00"}, "Bedspace Allocation": {"arrival": "13:09:48 PM", "start": "13:09:48 PM", "finish": "13:15:50 PM", "delay": "0:00:00", "occupancy": "362.37 seconds"}}, "Patient 97": {"criticality": "Level 3", "Registration": {"arrival": "13:05:18 PM", "start": "13:05:43 PM", "finish": "13:12:46 PM", "delay": "0:00:25.881935"}, "Bedspace Allocation": {"arrival": "13:12:46 PM", "start": "13:12:46 PM", "finish": "13:18:49 PM", "delay": "0:00:00", "occupancy": "362.50 seconds"}, "Consultation": {"arrival": "13:18:49 PM", "start": "13:18:49 PM", "finish": "13:32:52 PM", "delay": "0:00:00"}}, "Patient 98": {"criticality": "Level 1", "Bedspace Allocation": {"arrival": "13:07:09 PM", "start": "13:07:09 PM", "finish": "13:13:13 PM", "delay": "0:00:00", "occupancy": "364.54 seconds"}, "Registration": {"arrival": "13:13:13 PM", "start": "13:13:13 PM", "finish": "13:20:14 PM", "delay": "0:00:00"}, "Billing": {"arrival": "13:20:14 PM", "start": "13:20:14 PM", "finish": "13:30:19 PM", "delay": "0:00:00"}, "Scan": {"arrival": "13:30:19 PM", "start": "13:30:42 PM", "finish": "13:58:45 PM", "delay": "0:00:23.605270"}}, "Patient 99": {"criticality": "Level 1", "Bedspace Allocation": {"arrival": "13:07:58 PM", "start": "13:07:58 PM", "finish": "13:13:58 PM", "delay": "0:00:00", "occupancy": "360.93 seconds"}, "Registration": {"arrival": "13:13:58 PM", "start": "13:13:58 PM", "finish": "13:21:00 PM", "delay": "0:00:00"}, "Billing": {"arrival": "13:21:00 PM", "start": "13:21:00 PM", "finish": "13:31:01 PM", "delay": "0:00:00"}, "Scan": {"arrival": "13:31:01 PM", "start": "13:35:10 PM", "finish": "14:03:12 PM", "delay": "0:04:09.360781"}}, "Patient 100": {"criticality": "Level 2", "Registration": {"arrival": "13:12:04 PM", "start": "13:12:04 PM", "finish": "13:19:08 PM", "delay": "0:00:00"}, "Bedspace Allocation": {"arrival": "13:19:08 PM", "start": "13:19:08 PM", "finish": "13:25:11 PM", "delay": "0:00:00", "occupancy": "362.73 seconds"}, "Xray": {"arrival": "13:25:11 PM", "start": "13:25:11 PM", "finish": "13:46:13 PM", "delay": "0:00:00"}}, "Patient 101": {"criticality": "Level 2", "Registration": {"arrival": "13:14:26 PM", "start": "13:14:26 PM", "finish": "13:21:28 PM", "delay": "0:00:00"}, "Bedspace Allocation": {"arrival": "13:21:28 PM", "start": "13:21:28 PM", "finish": "13:27:31 PM", "delay": "0:00:00", "occupancy": "363.17 seconds"}, "Consultation": {"arrival": "13:27:31 PM", "start": "13:27:31 PM", "finish": "13:41:31 PM", "delay": "0:00:00"}, "Billing": {"arrival": "13:41:31 PM", "start": "13:41:31 PM", "finish": "13:51:31 PM", "delay": "0:00:00"}, "Pharmacy": {"arrival": "13:51:31 PM", "start": "13:54:56 PM", "finish": "14:09:58 PM", "delay": "0:03:24.692477"}, "Dressing": {"arrival": "14:09:58 PM", "start": "14:09:58 PM", "finish": "14:25:02 PM", "delay": "0:00:00.482224"}}, "Patient 102": {"criticality": "Level 2", "Registration": {"arrival": "13:29:37 PM", "start": "13:29:37 PM", "finish": "13:36:39 PM", "delay": "0:00:00"}, "Bedspace Allocation": {"arrival": "13:36:39 PM", "start": "13:36:39 PM", "finish": "13:42:40 PM", "delay": "0:00:00", "occupancy": "360.51 seconds"}, "Consultation": {"arrival": "14:27:43 PM", "start": "14:27:43 PM", "finish": "14:41:47 PM", "delay": "0:00:00"}, "Billing": {"arrival": "13:56:41 PM", "start": "13:56:41 PM", "finish": "14:06:42 PM", "delay": "0:00:00"}, "Xray": {"arrival": "14:06:42 PM", "start": "14:06:42 PM", "finish": "14:27:43 PM", "delay": "0:00:00"}}, "Patient 103": {"criticality": "Level 2", "Registration": {"arrival": "13:31:11 PM", "start": "13:31:11 PM", "finish": "13:38:11 PM", "delay": "0:00:00"}, "Bedspace Allocation": {"arrival": "13:38:11 PM", "start": "13:38:11 PM", "finish": "13:44:12 PM", "delay": "0:00:00", "occupancy": "360.61 seconds"}, "Consultation": {"arrival": "13:44:12 PM", "start": "13:44:12 PM", "finish": "13:58:12 PM", "delay": "0:00:00"}, "Billing": {"arrival": "13:58:12 PM", "start": "13:58:12 PM", "finish": "14:08:13 PM", "delay": "0:00:00"}, "Pharmacy": {"arrival": "14:08:13 PM", "start": "14:08:13 PM", "finish": "14:23:14 PM", "delay": "0:00:00"}}, "Patient 104": {"criticality": "Level 3", "Registration": {"arrival": "13:40:20 PM", "start": "13:40:20 PM", "finish": "13:47:20 PM", "delay": "0:00:00"}, "Bedspace Allocation": {"arrival": "13:47:20 PM", "start": "13:47:20 PM", "finish": "13:53:23 PM", "delay": "0:00:00", "occupancy": "362.60 seconds"}, "Consultation": {"arrival": "13:53:23 PM", "start": "13:53:23 PM", "finish": "14:07:26 PM", "delay": "0:00:00"}}, "Patient 105": {"criticality": "Level 1", "Bedspace Allocation": {"arrival": "13:45:53 PM", "start": "13:45:53 PM", "finish": "13:51:53 PM", "delay": "0:00:00", "occupancy": "360.03 seconds"}, "Registration": {"arrival": "13:51:53 PM", "start": "13:51:53 PM", "finish": "13:58:53 PM", "delay": "0:00:00"}, "Consultation": {"arrival": "13:58:53 PM", "start": "13:58:53 PM", "finish": "14:12:56 PM", "delay": "0:00:00"}, "Billing": {"arrival": "14:12:56 PM", "start": "14:12:56 PM", "finish": "14:23:00 PM", "delay": "0:00:00"}, "Injection": {"arrival": "14:23:00 PM", "start": "14:23:00 PM", "finish": "14:34:02 PM", "delay": "0:00:00"}}, "Patient 106": {"criticality": "Level 3", "Registration": {"arrival": "13:46:24 PM", "start": "13:46:24 PM", "finish": "13:53:28 PM", "delay": "0:00:00"}, "Bedspace Allocation": {"arrival": "13:53:28 PM", "start": "13:53:28 PM", "finish": "13:59:30 PM", "delay": "0:00:00", "occupancy": "361.91 seconds"}, "Consultation": {"arrival": "14:44:39 PM", "start": "14:44:39 PM", "finish": "14:58:42 PM", "delay": "0:00:00"}, "Billing": {"arrival": "14:58:42 PM", "start": "14:58:42 PM", "finish": "15:08:45 PM", "delay": "0:00:00"}, "Xray": {"arrival": "14:23:35 PM", "start": "14:23:35 PM", "finish": "14:44:39 PM", "delay": "0:00:00"}, "Pharmacy": {"arrival": "15:08:45 PM", "start": "15:08:45 PM", "finish": "15:23:49 PM", "delay": "0:00:00"}, "Dressing": {"arrival": "15:23:49 PM", "start": "15:23:49 PM", "finish": "15:38:52 PM", "delay": "0:00:00"}}, "Patient 107": {"criticality": "Level 2", "Registration": {"arrival": "13:48:16 PM", "start": "13:48:16 PM", "finish": "13:55:19 PM", "delay": "0:00:00"}, "Bedspace Allocation": {"arrival": "13:55:19 PM", "start": "13:55:19 PM", "finish": "14:01:22 PM", "delay": "0:00:00", "occupancy": "363.25 seconds"}, "Billing": {"arrival": "14:01:22 PM", "start": "14:01:22 PM", "finish": "14:11:23 PM", "delay": "0:00:00"}, "Scan": {"arrival": "14:11:23 PM", "start": "14:11:23 PM", "finish": "14:39:24 PM", "delay": "0:00:00"}}, "Patient 108": {"criticality": "Level 3", "Registration": {"arrival": "13:50:05 PM", "start": "13:50:05 PM", "finish": "13:57:05 PM", "delay": "0:00:00"}, "Bedspace Allocation": {"arrival": "13:57:05 PM", "start": "13:57:05 PM", "finish": "14:03:08 PM", "delay": "0:00:00", "occupancy": "363.72 seconds"}, "Consultation": {"arrival": "14:48:45 PM", "start": "14:48:45 PM", "finish": "15:02:45 PM", "delay": "0:00:00"}, "Billing": {"arrival": "14:17:11 PM", "start": "14:17:11 PM", "finish": "14:27:12 PM", "delay": "0:00:00"}, "Xray": {"arrival": "14:27:12 PM", "start": "14:27:43 PM", "finish": "14:48:45 PM", "delay": "0:00:30.708676"}}, "Patient 109": {"criticality": "Level 2", "Registration": {"arrival": "13:59:08 PM", "start": "13:59:08 PM", "finish": "14:06:08 PM", "delay": "0:00:00"}, "Bedspace Allocation": {"arrival": "14:06:08 PM", "start": "14:06:08 PM", "finish": "14:12:10 PM", "delay": "0:00:00", "occupancy": "361.42 seconds"}, "Billing": {"arrival": "14:12:10 PM", "start": "14:12:10 PM", "finish": "14:22:12 PM", "delay": "0:00:00"}, "Xray": {"arrival": "14:22:12 PM", "start": "14:22:12 PM", "finish": "14:43:16 PM", "delay": "0:00:00"}}, "Patient 110": {"criticality": "Level 2", "Registration": {"arrival": "14:02:32 PM", "start": "14:02:32 PM", "finish": "14:09:32 PM", "delay": "0:00:00"}, "Bedspace Allocation": {"arrival": "14:09:32 PM", "start": "14:09:32 PM", "finish": "14:15:35 PM", "delay": "0:00:00", "occupancy": "362.22 seconds"}, "Consultation": {"arrival": "14:15:35 PM", "start": "14:15:35 PM", "finish": "14:29:36 PM", "delay": "0:00:00"}, "Billing": {"arrival": "14:29:36 PM", "start": "14:29:36 PM", "finish": "14:39:41 PM", "delay": "0:00:00"}, "Pharmacy": {"arrival": "14:39:41 PM", "start": "14:39:41 PM", "finish": "14:54:42 PM", "delay": "0:00:00"}}, "Patient 111": {"criticality": "Level 1", "Bedspace Allocation": {"arrival": "14:08:48 PM", "start": "14:08:48 PM", "finish": "14:14:49 PM", "delay": "0:00:00", "occupancy": "361.35 seconds"}, "Registration": {"arrival": "14:14:49 PM", "start": "14:14:49 PM", "finish": "14:21:50 PM", "delay": "0:00:00"}, "Consultation": {"arrival": "14:21:50 PM", "start": "14:21:50 PM", "finish": "14:35:52 PM", "delay": "0:00:00"}}, "Patient 112": {"criticality": "Level 1", "Bedspace Allocation": {"arrival": "14:09:53 PM", "start": "14:09:53 PM", "finish": "14:15:53 PM", "delay": "0:00:00", "occupancy": "360.45 seconds"}, "Registration": {"arrival": "14:15:53 PM", "start": "14:15:53 PM", "finish": "14:22:56 PM", "delay": "0:00:00"}, "Consultation": {"arrival": "14:22:56 PM", "start": "14:22:56 PM", "finish": "14:36:59 PM", "delay": "0:00:00"}}, "Patient 113": {"criticality": "Level 3", "Registration": {"arrival": "14:10:29 PM", "start": "14:10:29 PM", "finish": "14:17:29 PM", "delay": "0:00:00"}, "Bedspace Allocation": {"arrival": "14:17:29 PM", "start": "14:17:29 PM", "finish": "14:23:32 PM", "delay": "0:00:00", "occupancy": "363.21 seconds"}, "Billing": {"arrival": "14:23:32 PM", "start": "14:23:32 PM", "finish": "14:33:35 PM", "delay": "0:00:00"}, "Scan": {"arrival": "14:33:35 PM", "start": "14:33:35 PM", "finish": "15:01:36 PM", "delay": "0:00:00"}}, "Patient 114": {"criticality": "Level 3", "Registration": {"arrival": "14:11:25 PM", "start": "14:11:25 PM", "finish": "14:18:29 PM", "delay": "0:00:00"}, "Bedspace Allocation": {"arrival": "14:18:29 PM", "start": "14:18:29 PM", "finish": "14:24:30 PM", "delay": "0:00:00", "occupancy": "361.25 seconds"}, "Xray": {"arrival": "14:24:30 PM", "start": "14:24:30 PM", "finish": "14:45:32 PM", "delay": "0:00:00"}}, "Patient 115": {"criticality": "Level 1", "Bedspace Allocation": {"arrival": "14:16:07 PM", "start": "14:16:07 PM", "finish": "14:22:09 PM", "delay": "0:00:00", "occupancy": "362.51 seconds"}, "Registration": {"arrival": "14:22:09 PM", "start": "14:22:09 PM", "finish": "14:29:10 PM", "delay": "0:00:00"}, "Billing": {"arrival": "15:18:21 PM", "start": "15:22:59 PM", "finish": "15:33:04 PM", "delay": "0:04:38.939346"}, "Xray": {"arrival": "14:39:13 PM", "start": "14:43:16 PM", "finish": "15:04:20 PM", "delay": "0:04:03.462733"}, "Consultation": {"arrival": "15:04:20 PM", "start": "15:04:20 PM", "finish": "15:18:21 PM", "delay": "0:00:00"}, "Pharmacy": {"arrival": "15:33:04 PM", "start": "15:33:04 PM", "finish": "15:48:09 PM", "delay": "0:00:00"}}, "Patient 116": {"criticality": "Level 1", "Bedspace Allocation": {"arrival": "14:19:48 PM", "start": "14:19:48 PM", "finish": "14:25:48 PM", "delay": "0:00:00", "occupancy": "360.47 seconds"}, "Registration": {"arrival": "14:25:48 PM", "start": "14:27:22 PM", "finish": "14:34:25 PM", "delay": "0:01:34.251643"}, "Billing": {"arrival": "14:34:25 PM", "start": "14:34:25 PM", "finish": "14:44:26 PM", "delay": "0:00:00"}, "Scan": {"arrival": "14:44:26 PM", "start": "14:44:26 PM", "finish": "15:12:27 PM", "delay": "0:00:00"}}, "Patient 117": {"criticality": "Level 2", "Registration": {"arrival": "14:20:20 PM", "start": "14:20:20 PM", "finish": "14:27:22 PM", "delay": "0:00:00"}, "Bedspace Allocation": {"arrival": "14:27:22 PM", "start": "14:27:22 PM", "finish": "14:33:25 PM", "delay": "0:00:00", "occupancy": "363.18 seconds"}, "Consultation": {"arrival": "14:33:25 PM", "start": "14:33:25 PM", "finish": "14:47:29 PM", "delay": "0:00:00"}, "Billing": {"arrival": "14:47:29 PM", "start": "14:47:29 PM", "finish": "14:57:31 PM", "delay": "0:00:00"}, "Pharmacy": {"arrival": "14:57:31 PM", "start": "14:57:31 PM", "finish": "15:12:33 PM", "delay": "0:00:00"}}, "Patient 118": {"criticality": "Level 2", "Registration": {"arrival": "14:22:01 PM", "start": "14:22:01 PM", "finish": "14:29:03 PM", "delay": "0:00:00"}, "Bedspace Allocation": {"arrival": "14:29:03 PM", "start": "14:29:03 PM", "finish": "14:35:06 PM", "delay": "0:00:00", "occupancy": "363.30 seconds"}, "Billing": {"arrival": "14:35:06 PM", "start": "14:35:06 PM", "finish": "14:45:10 PM", "delay": "0:00:00"}, "Scan": {"arrival": "14:45:10 PM", "start": "14:45:10 PM", "finish": "15:13:12 PM", "delay": "0:00:00"}}, "Patient 119": {"criticality": "Level 3", "Registration": {"arrival": "14:23:53 PM", "start": "14:23:53 PM", "finish": "14:30:55 PM", "delay": "0:00:00"}, "Bedspace Allocation": {"arrival": "14:30:55 PM", "start": "14:30:55 PM", "finish": "14:36:59 PM", "delay": "0:00:00", "occupancy": "364.22 seconds"}, "Consultation": {"arrival": "14:36:59 PM", "start": "14:36:59 PM", "finish": "14:51:01 PM", "delay": "0:00:00"}, "Billing": {"arrival": "14:51:01 PM", "start": "14:51:01 PM", "finish": "15:01:06 PM", "delay": "0:00:00"}, "Pharmacy": {"arrival": "15:01:06 PM", "start": "15:01:06 PM", "finish": "15:16:10 PM", "delay": "0:00:00"}}, "Patient 120": {"criticality": "Level 1", "Bedspace Allocation": {"arrival": "14:24:38 PM", "start": "14:24:38 PM", "finish": "14:30:38 PM", "delay": "0:00:00", "occupancy": "360.15 seconds"}, "Registration": {"arrival": "14:30:38 PM", "start": "14:30:55 PM", "finish": "14:37:56 PM", "delay": "0:00:17.227420"}, "Consultation": {"arrival": "14:37:56 PM", "start": "14:37:56 PM", "finish": "14:51:56 PM", "delay": "0:00:00"}, "Billing": {"arrival": "14:51:56 PM", "start": "14:51:56 PM", "finish": "15:02:01 PM", "delay": "0:00:00"}, "Xray": {"arrival": "15:02:01 PM", "start": "15:02:01 PM", "finish": "15:23:02 PM", "delay": "0:00:00"}}, "Patient 121": {"criticality": "Level 2", "Registration": {"arrival": "14:24:50 PM", "start": "14:24:50 PM", "finish": "14:31:54 PM", "delay": "0:00:00"}, "Bedspace Allocation": {"arrival": "14:31:54 PM", "start": "14:31:54 PM", "finish": "14:37:54 PM", "delay": "0:00:00", "occupancy": "360.25 seconds"}, "Billing": {"arrival": "15:10:19 PM", "start": "15:10:19 PM", "finish": "15:20:19 PM", "delay": "0:00:00"}, "Xray": {"arrival": "14:49:15 PM", "start": "14:49:15 PM", "finish": "15:10:19 PM", "delay": "0:00:00"}, "Pharmacy": {"arrival": "15:20:19 PM", "start": "15:20:19 PM", "finish": "15:35:22 PM", "delay": "0:00:00"}, "Dressing": {"arrival": "15:35:22 PM", "start": "15:53:57 PM", "finish": "16:09:00 PM", "delay": "0:18:34.840650"}}, "Patient 122": {"criticality": "Level 2", "Registration": {"arrival": "14:28:08 PM", "start": "14:29:03 PM", "finish": "14:36:03 PM", "delay": "0:00:55.559412"}, "Bedspace Allocation": {"arrival": "14:36:03 PM", "start": "14:36:03 PM", "finish": "14:42:06 PM", "delay": "0:00:00", "occupancy": "362.44 seconds"}, "Consultation": {"arrival": "14:42:06 PM", "start": "14:42:06 PM", "finish": "14:56:10 PM", "delay": "0:00:00"}, "Billing": {"arrival": "14:56:10 PM", "start": "14:56:10 PM", "finish": "15:06:10 PM", "delay": "0:00:00"}, "Pharmacy": {"arrival": "15:06:10 PM", "start": "15:06:10 PM", "finish": "15:21:11 PM", "delay": "0:00:00"}}, "Patient 123": {"criticality": "Level 3", "Registration": {"arrival": "14:30:02 PM", "start": "14:30:02 PM", "finish": "14:37:04 PM", "delay": "0:00:00"}, "Bedspace Allocation": {"arrival": "14:37:04 PM", "start": "14:37:04 PM", "finish": "14:43:05 PM", "delay": "0:00:00", "occupancy": "360.87 seconds"}, "Billing": {"arrival": "15:14:10 PM", "start": "15:14:10 PM", "finish": "15:24:11 PM", "delay": "0:00:00"}, "Xray": {"arrival": "14:53:10 PM", "start": "14:53:10 PM", "finish": "15:14:10 PM", "delay": "0:00:00"}, "Pharmacy": {"arrival": "15:24:11 PM", "start": "15:24:11 PM", "finish": "15:39:11 PM", "delay": "0:00:00"}, "Dressing": {"arrival": "15:39:11 PM", "start": "16:24:02 PM", "finish": "16:39:03 PM", "delay": "0:44:51.041713"}}, "Patient 124": {"criticality": "Level 1", "Bedspace Allocation": {"arrival": "14:32:45 PM", "start": "14:32:45 PM", "finish": "14:38:45 PM", "delay": "0:00:00", "occupancy": "360.89 seconds"}, "Registration": {"arrival": "14:38:45 PM", "start": "14:38:45 PM", "finish": "14:45:48 PM", "delay": "0:00:00"}, "Consultation": {"arrival": "14:45:48 PM", "start": "14:45:48 PM", "finish": "14:59:52 PM", "delay": "0:00:00"}, "Billing": {"arrival": "14:59:52 PM", "start": "15:01:06 PM", "finish": "15:11:06 PM", "delay": "0:01:13.130687"}, "Pharmacy": {"arrival": "15:11:06 PM", "start": "15:12:33 PM", "finish": "15:27:35 PM", "delay": "0:01:26.647870"}, "Dressing": {"arrival": "15:27:35 PM", "start": "15:38:52 PM", "finish": "15:53:57 PM", "delay": "0:11:17.519607"}}, "Patient 125": {"criticality": "Level 1", "Bedspace Allocation": {"arrival": "14:41:13 PM", "start": "14:41:13 PM", "finish": "14:47:17 PM", "delay": "0:00:00", "occupancy": "364.17 seconds"}, "Registration": {"arrival": "14:47:17 PM", "start": "14:47:17 PM", "finish": "14:54:22 PM", "delay": "0:00:00"}, "Consultation": {"arrival": "14:54:22 PM", "start": "14:54:22 PM", "finish": "15:08:26 PM", "delay": "0:00:00"}}, "Patient 126": {"criticality": "Level 2", "Registration": {"arrival": "14:45:49 PM", "start": "14:45:49 PM", "finish": "14:52:50 PM", "delay": "0:00:00"}, "Bedspace Allocation": {"arrival": "14:52:50 PM", "start": "14:52:50 PM", "finish": "14:58:53 PM", "delay": "0:00:00", "occupancy": "363.37 seconds"}, "Consultation": {"arrival": "14:58:53 PM", "start": "14:58:53 PM", "finish": "15:12:56 PM", "delay": "0:00:00"}, "Billing": {"arrival": "15:12:56 PM", "start": "15:12:56 PM", "finish": "15:22:59 PM", "delay": "0:00:00"}, "Scan": {"arrival": "15:22:59 PM", "start": "15:22:59 PM", "finish": "15:51:03 PM", "delay": "0:00:00"}}, "Patient 127": {"criticality": "Level 1", "Bedspace Allocation": {"arrival": "14:48:19 PM", "start": "14:48:19 PM", "finish": "14:54:22 PM", "delay": "0:00:00", "occupancy": "363.36 seconds"}, "Registration": {"arrival": "14:54:22 PM", "start": "14:54:22 PM", "finish": "15:01:23 PM", "delay": "0:00:00"}, "Billing": {"arrival": "15:01:23 PM", "start": "15:02:01 PM", "finish": "15:12:05 PM", "delay": "0:00:37.792472"}, "Xray": {"arrival": "15:12:05 PM", "start": "15:12:05 PM", "finish": "15:33:10 PM", "delay": "0:00:00"}}, "Patient 128": {"criticality": "Level 1", "Bedspace Allocation": {"arrival": "14:49:37 PM", "start": "14:49:37 PM", "finish": "14:55:39 PM", "delay": "0:00:00", "occupancy": "362.39 seconds"}, "Registration": {"arrival": "14:55:39 PM", "start": "14:55:39 PM", "finish": "15:02:42 PM", "delay": "0:00:00"}, "Consultation": {"arrival": "15:02:42 PM", "start": "15:02:42 PM", "finish": "15:16:43 PM", "delay": "0:00:00"}, "Billing": {"arrival": "15:16:43 PM", "start": "15:20:19 PM", "finish": "15:30:22 PM", "delay": "0:03:36.351171"}, "Xray": {"arrival": "15:30:22 PM", "start": "15:30:22 PM", "finish": "15:51:23 PM", "delay": "0:00:00"}}, "Patient 129": {"criticality": "Level 2", "Registration": {"arrival": "14:51:16 PM", "start": "14:51:16 PM", "finish": "14:58:17 PM", "delay": "0:00:00"}, "Bedspace Allocation": {"arrival": "14:58:17 PM", "start": "14:58:17 PM", "finish": "15:04:18 PM", "delay": "0:00:00", "occupancy": "360.85 seconds"}, "Consultation": {"arrival": "15:04:18 PM", "start": "15:04:18 PM", "finish": "15:18:22 PM", "delay": "0:00:00"}, "Billing": {"arrival": "15:18:22 PM", "start": "15:24:11 PM", "finish": "15:34:12 PM", "delay": "0:05:48.905122"}, "Pharmacy": {"arrival": "15:34:12 PM", "start": "15:34:12 PM", "finish": "15:49:17 PM", "delay": "0:00:00"}}, "Patient 130": {"criticality": "Level 2", "Registration": {"arrival": "14:52:41 PM", "start": "14:52:41 PM", "finish": "14:59:41 PM", "delay": "0:00:00"}, "Bedspace Allocation": {"arrival": "14:59:41 PM", "start": "14:59:41 PM", "finish": "15:05:46 PM", "delay": "0:00:00", "occupancy": "364.47 seconds"}, "Consultation": {"arrival": "15:05:46 PM", "start": "15:05:46 PM", "finish": "15:19:47 PM", "delay": "0:00:00"}, "Billing": {"arrival": "15:19:47 PM", "start": "15:26:03 PM", "finish": "15:36:05 PM", "delay": "0:06:15.868675"}, "Dressing": {"arrival": "15:36:05 PM", "start": "16:09:00 PM", "finish": "16:24:02 PM", "delay": "0:32:55.141638"}}, "Patient 131": {"criticality": "Level 3", "Registration": {"arrival": "15:00:40 PM", "start": "15:00:40 PM", "finish": "15:07:41 PM", "delay": "0:00:00"}, "Bedspace Allocation": {"arrival": "15:07:41 PM", "start": "15:07:41 PM", "finish": "15:13:43 PM", "delay": "0:00:00", "occupancy": "362.61 seconds"}, "Consultation": {"arrival": "15:13:43 PM", "start": "15:13:43 PM", "finish": "15:27:47 PM", "delay": "0:00:00"}}, "Patient 132": {"criticality": "Level 2", "Registration": {"arrival": "15:02:58 PM", "start": "15:02:58 PM", "finish": "15:09:59 PM", "delay": "0:00:00"}, "Bedspace Allocation": {"arrival": "15:09:59 PM", "start": "15:09:59 PM", "finish": "15:15:59 PM", "delay": "0:00:00", "occupancy": "360.60 seconds"}, "Billing": {"arrival": "15:47:03 PM", "start": "15:47:03 PM", "finish": "15:57:04 PM", "delay": "0:00:00"}, "Xray": {"arrival": "15:26:03 PM", "start": "15:26:03 PM", "finish": "15:47:03 PM", "delay": "0:00:00"}, "Pharmacy": {"arrival": "15:57:04 PM", "start": "15:57:04 PM", "finish": "16:12:06 PM", "delay": "0:00:00"}}, "Patient 133": {"criticality": "Level 1", "Bedspace Allocation": {"arrival": "15:06:18 PM", "start": "15:06:18 PM", "finish": "15:12:21 PM", "delay": "0:00:00", "occupancy": "363.23 seconds"}, "Registration": {"arrival": "15:12:21 PM", "start": "15:12:21 PM", "finish": "15:19:24 PM", "delay": "0:00:00"}, "Xray": {"arrival": "15:19:24 PM", "start": "15:19:24 PM", "finish": "15:40:25 PM", "delay": "0:00:00"}}, "Patient 134": {"criticality": "Level 1", "Bedspace Allocation": {"arrival": "15:07:05 PM", "start": "15:07:05 PM", "finish": "15:13:08 PM", "delay": "0:00:00", "occupancy": "363.47 seconds"}, "Registration": {"arrival": "15:13:08 PM", "start": "15:13:08 PM", "finish": "15:20:09 PM", "delay": "0:00:00"}, "Consultation": {"arrival": "15:20:09 PM", "start": "15:20:09 PM", "finish": "15:34:11 PM", "delay": "0:00:00"}}, "Patient 135": {"criticality": "Level 3", "Registration": {"arrival": "15:15:20 PM", "start": "15:15:20 PM", "finish": "15:22:20 PM", "delay": "0:00:00"}, "Bedspace Allocation": {"arrival": "15:22:20 PM", "start": "15:22:20 PM", "finish": "15:28:23 PM", "delay": "0:00:00", "occupancy": "362.28 seconds"}, "Billing": {"arrival": "15:28:23 PM", "start": "15:30:22 PM", "finish": "15:40:26 PM", "delay": "0:01:58.934263"}, "Scan": {"arrival": "15:40:26 PM", "start": "15:40:26 PM", "finish": "16:08:28 PM", "delay": "0:00:00"}}, "Patient 136": {"criticality": "Level 2", "Registration": {"arrival": "15:17:51 PM", "start": "15:17:51 PM", "finish": "15:24:52 PM", "delay": "0:00:00"}, "Bedspace Allocation": {"arrival": "15:24:52 PM", "start": "15:24:52 PM", "finish": "15:30:57 PM", "delay": "0:00:00", "occupancy": "364.81 seconds"}, "Consultation": {"arrival": "15:30:57 PM", "start": "15:30:57 PM", "finish": "15:44:59 PM", "delay": "0:00:00"}, "Billing": {"arrival": "15:44:59 PM", "start": "15:44:59 PM", "finish": "15:55:00 PM", "delay": "0:00:00"}, "Dressing": {"arrival": "15:55:00 PM", "start": "16:39:03 PM", "finish": "16:54:06 PM", "delay": "0:44:02.315559"}}, "Patient 137": {"criticality": "Level 3", "Registration": {"arrival": "15:20:20 PM", "start": "15:20:20 PM", "finish": "15:27:22 PM", "delay": "0:00:00"}, "Bedspace Allocation": {"arrival": "15:27:22 PM", "start": "15:27:22 PM", "finish": "15:33:23 PM", "delay": "0:00:00", "occupancy": "360.50 seconds"}, "Consultation": {"arrival": "15:33:23 PM", "start": "15:33:23 PM", "finish": "15:47:23 PM", "delay": "0:00:00"}, "Billing": {"arrival": "15:47:23 PM", "start": "15:47:23 PM", "finish": "15:57:26 PM", "delay": "0:00:00"}, "Pharmacy": {"arrival": "15:57:26 PM", "start": "15:57:26 PM", "finish": "16:12:29 PM", "delay": "0:00:00"}}, "Patient 138": {"criticality": "Level 1", "Bedspace Allocation": {"arrival": "15:22:44 PM", "start": "15:22:44 PM", "finish": "15:28:48 PM", "delay": "0:00:00", "occupancy": "364.84 seconds"}, "Registration": {"arrival": "15:28:48 PM", "start": "15:28:48 PM", "finish": "15:35:51 PM", "delay": "0:00:00"}, "Billing": {"arrival": "16:07:01 PM", "start": "16:07:01 PM", "finish": "16:17:01 PM", "delay": "0:00:00"}, "Xray": {"arrival": "15:45:56 PM", "start": "15:45:56 PM", "finish": "16:07:01 PM", "delay": "0:00:00"}, "Pharmacy": {"arrival": "16:17:01 PM", "start": "16:17:01 PM", "finish": "16:32:02 PM", "delay": "0:00:00"}, "Dressing": {"arrival": "16:32:02 PM", "start": "17:09:09 PM", "finish": "17:24:10 PM", "delay": "0:37:07.191527"}}, "Patient 139": {"criticality": "Level 1", "Bedspace Allocation": {"arrival": "15:24:30 PM", "start": "15:24:30 PM", "finish": "15:30:32 PM", "delay": "0:00:00", "occupancy": "362.58 seconds"}, "Registration": {"arrival": "15:30:32 PM", "start": "15:30:32 PM", "finish": "15:37:34 PM", "delay": "0:00:00"}, "Consultation": {"arrival": "15:37:34 PM", "start": "15:37:34 PM", "finish": "15:51:34 PM", "delay": "0:00:00"}, "Billing": {"arrival": "15:51:34 PM", "start": "15:51:34 PM", "finish": "16:01:39 PM", "delay": "0:00:00"}, "Pharmacy": {"arrival": "16:01:39 PM", "start": "16:01:39 PM", "finish": "16:16:42 PM", "delay": "0:00:00"}, "Dressing": {"arrival": "16:16:42 PM", "start": "16:54:06 PM", "finish": "17:09:09 PM", "delay": "0:37:23.759227"}}, "Patient 140": {"criticality": "Level 3", "Registration": {"arrival": "15:41:30 PM", "start": "15:41:30 PM", "finish": "15:48:33 PM", "delay": "0:00:00"}, "Bedspace Allocation": {"arrival": "15:48:33 PM", "start": "15:48:33 PM", "finish": "15:54:37 PM", "delay": "0:00:00", "occupancy": "363.79 seconds"}, "Consultation": {"arrival": "15:54:37 PM", "start": "15:54:37 PM", "finish": "16:08:39 PM", "delay": "0:00:00"}, "Billing": {"arrival": "16:08:39 PM", "start": "16:08:39 PM", "finish": "16:18:43 PM", "delay": "0:00:00"}, "Pharmacy": {"arrival": "16:18:43 PM", "start": "16:18:43 PM", "finish": "16:33:45 PM", "delay": "0:00:00"}, "Dressing": {"arrival": "16:33:45 PM", "start": "17:24:10 PM", "finish": "17:39:13 PM", "delay": "0:50:24.899464"}}, "Patient 141": {"criticality": "Level 2", "Registration": {"arrival": "15:49:14 PM", "start": "15:49:14 PM", "finish": "15:56:18 PM", "delay": "0:00:00"}, "Bedspace Allocation": {"arrival": "15:56:18 PM", "start": "15:56:18 PM", "finish": "16:02:22 PM", "delay": "0:00:00", "occupancy": "363.22 seconds"}, "Consultation": {"arrival": "16:02:22 PM", "start": "16:02:22 PM", "finish": "16:16:25 PM", "delay": "0:00:00"}}, "Patient 142": {"criticality": "Level 1", "Bedspace Allocation": {"arrival": "15:52:58 PM", "start": "15:52:58 PM", "finish": "15:58:58 PM", "delay": "0:00:00", "occupancy": "360.25 seconds"}, "Registration": {"arrival": "15:58:58 PM", "start": "15:58:58 PM", "finish": "16:06:01 PM", "delay": "0:00:00"}, "Consultation": {"arrival": "16:06:01 PM", "start": "16:06:01 PM", "finish": "16:20:03 PM", "delay": "0:00:00"}, "Billing": {"arrival": "16:20:03 PM", "start": "16:20:03 PM", "finish": "16:30:06 PM", "delay": "0:00:00"}, "Pharmacy": {"arrival": "16:30:06 PM", "start": "16:30:06 PM", "finish": "16:45:08 PM", "delay": "0:00:00"}}, "Patient 143": {"criticality": "Level 2", "Registration": {"arrival": "15:55:38 PM", "start": "15:55:38 PM", "finish": "16:02:40 PM", "delay": "0:00:00"}, "Bedspace Allocation": {"arrival": "16:02:40 PM", "start": "16:02:40 PM", "finish": "16:08:41 PM", "delay": "0:00:00", "occupancy": "361.03 seconds"}, "Consultation": {"arrival": "16:08:41 PM", "start": "16:08:41 PM", "finish": "16:22:42 PM", "delay": "0:00:00"}, "Billing": {"arrival": "16:22:42 PM", "start": "16:22:42 PM", "finish": "16:32:43 PM", "delay": "0:00:00"}, "Pharmacy": {"arrival": "16:32:43 PM", "start": "16:32:43 PM", "finish": "16:47:45 PM", "delay": "0:00:00"}}, "Patient 144": {"criticality": "Level 3", "Registration": {"arrival": "15:56:26 PM", "start": "15:56:26 PM", "finish": "16:03:30 PM", "delay": "0:00:00"}, "Bedspace Allocation": {"arrival": "16:03:30 PM", "start": "16:03:30 PM", "finish": "16:09:34 PM", "delay": "0:00:00", "occupancy": "364.32 seconds"}, "Consultation": {"arrival": "16:09:34 PM", "start": "16:09:34 PM", "finish": "16:23:38 PM", "delay": "0:00:00"}, "Billing": {"arrival": "16:23:38 PM", "start": "16:28:58 PM", "finish": "16:38:58 PM", "delay": "0:05:20.620498"}, "Pharmacy": {"arrival": "16:38:58 PM", "start": "16:38:58 PM", "finish": "16:53:58 PM", "delay": "0:00:00"}}, "Patient 145": {"criticality": "Level 1", "Bedspace Allocation": {"arrival": "16:00:39 PM", "start": "16:00:39 PM", "finish": "16:06:41 PM", "delay": "0:00:00", "occupancy": "362.09 seconds"}, "Registration": {"arrival": "16:06:41 PM", "start": "16:06:41 PM", "finish": "16:13:46 PM", "delay": "0:00:00"}, "Xray": {"arrival": "16:13:46 PM", "start": "16:13:46 PM", "finish": "16:34:50 PM", "delay": "0:00:00"}}, "Patient 146": {"criticality": "Level 1", "Bedspace Allocation": {"arrival": "16:05:48 PM", "start": "16:05:48 PM", "finish": "16:11:51 PM", "delay": "0:00:00", "occupancy": "363.35 seconds"}, "Registration": {"arrival": "16:11:51 PM", "start": "16:11:51 PM", "finish": "16:18:53 PM", "delay": "0:00:00"}, "Billing": {"arrival": "16:50:01 PM", "start": "16:50:01 PM", "finish": "17:00:05 PM", "delay": "0:00:00"}, "Xray": {"arrival": "16:28:58 PM", "start": "16:28:58 PM", "finish": "16:50:01 PM", "delay": "0:00:00"}, "Pharmacy": {"arrival": "17:00:05 PM", "start": "17:00:05 PM", "finish": "17:15:10 PM", "delay": "0:00:00"}, "Dressing": {"arrival": "17:15:10 PM", "start": "17:39:13 PM", "finish": "17:54:14 PM", "delay": "0:24:03.146051"}}, "Patient 147": {"criticality": "Level 2", "Registration": {"arrival": "16:07:03 PM", "start": "16:07:03 PM", "finish": "16:14:07 PM", "delay": "0:00:00"}, "Bedspace Allocation": {"arrival": "16:14:07 PM", "start": "16:14:07 PM", "finish": "16:20:07 PM", "delay": "0:00:00", "occupancy": "360.30 seconds"}, "Billing": {"arrival": "16:20:07 PM", "start": "16:20:07 PM", "finish": "16:30:11 PM", "delay": "0:00:00"}, "Scan": {"arrival": "16:30:11 PM", "start": "16:30:11 PM", "finish": "16:58:14 PM", "delay": "0:00:00"}}, "Patient 148": {"criticality": "Level 2", "Registration": {"arrival": "16:09:45 PM", "start": "16:09:45 PM", "finish": "16:16:47 PM", "delay": "0:00:00"}, "Bedspace Allocation": {"arrival": "16:16:47 PM", "start": "16:16:47 PM", "finish": "16:22:49 PM", "delay": "0:00:00", "occupancy": "361.58 seconds"}, "Consultation": {"arrival": "17:07:58 PM", "start": "17:07:58 PM", "finish": "17:22:03 PM", "delay": "0:00:00"}, "Billing": {"arrival": "17:22:03 PM", "start": "17:22:03 PM", "finish": "17:32:07 PM", "delay": "0:00:00"}, "Xray": {"arrival": "16:46:58 PM", "start": "16:46:58 PM", "finish": "17:07:58 PM", "delay": "0:00:00"}, "Pharmacy": {"arrival": "17:32:07 PM", "start": "17:32:07 PM", "finish": "17:47:08 PM", "delay": "0:00:00"}, "Dressing": {"arrival": "17:47:08 PM", "start": "17:54:14 PM", "finish": "18:09:14 PM", "delay": "0:07:05.645753"}}, "Patient 149": {"criticality": "Level 1", "Bedspace Allocation": {"arrival": "16:15:28 PM", "start": "16:15:28 PM", "finish": "16:21:31 PM", "delay": "0:00:00", "occupancy": "363.75 seconds"}, "Registration": {"arrival": "16:21:31 PM", "start": "16:21:31 PM", "finish": "16:28:34 PM", "delay": "0:00:00"}, "Billing": {"arrival": "16:28:34 PM", "start": "16:30:06 PM", "finish": "16:40:06 PM", "delay": "0:01:32.298517"}, "Xray": {"arrival": "16:40:06 PM", "start": "16:40:06 PM", "finish": "17:01:11 PM", "delay": "0:00:00"}}}